[{"n":"Dalles Disposal Service","o":"Other big prime contractors","a":"Logistics & Sustainment","s":"Maintenance, Repair & Operations","t":"Unknown technology","m":"The Dalles, OR","la":45.6109,"lo":-121.1982,"z":"97058","amt":128160,"b":"Army","v":"Dalles Disposal Service"},{"n":"Crestline Construction Company, L.l.c.","o":"Small prime contractors","a":"Construction","s":"Construction","t":"Unknown technology","m":"The Dalles, OR","la":45.625,"lo":-121.2001,"z":"97058","amt":31282,"b":"Army","v":"Crestline Construction Company, L.l.c."}]
