[{"n":"14solutions LLC","o":"Subcontractors","a":"Services","s":"Unknown sector","t":"Unknown technology","m":"Sanford, NC","la":35.4835,"lo":-79.1431,"z":"27330","amt":5346620,"b":"Unknown branch affiliation","v":"14solutions LLC"},{"n":"Operational Technical Solutions LLC","o":"Subcontractors","a":"Services","s":"Unknown sector","t":"Unknown technology","m":"Sanford, NC","la":35.4454,"lo":-79.1388,"z":"27332","amt":699968,"b":"Unknown branch affiliation","v":"Operational Technical Solutions LLC"},{"n":"Waste Management of Carolinas, INC.","o":"Other big prime contractors","a":"Logistics & Sustainment","s":"Unknown sector","t":"Unknown technology","m":"Sanford, NC","la":35.5043,"lo":-79.205,"z":"27330","amt":577944,"b":"Army","v":"Waste Management of Carolinas, INC."},{"n":"Air Systems Components INC","o":"Subcontractors","a":"Services","s":"Unknown sector","t":"Unknown technology","m":"Sanford, NC","la":35.513,"lo":-79.2135,"z":"27330","amt":188440,"b":"Unknown branch affiliation","v":"Air Systems Components INC"},{"n":"Evan CORP","o":"Other big prime contractors","a":"Logistics & Sustainment","s":"Aircraft & Aviation;Construction;Engineering & Technical Services;Maintenance, Repair & Operations","t":"Unknown technology","m":"Sanford, NC","la":35.4446,"lo":-79.1442,"z":"27332","amt":131848,"b":"Air Force;Army;Navy","v":"Evan CORP"},{"n":"Aero Avionics INC","o":"Small prime contractors","a":"Production","s":"Aircraft & Aviation","t":"Unknown technology","m":"Sanford, NC","la":35.579,"lo":-79.1091,"z":"27330","amt":60825,"b":"Navy","v":"Aero Avionics INC"},{"n":"Olivia Machine & Tool, INC.","o":"Subcontractors","a":"Services","s":"Unknown sector","t":"Unknown technology","m":"Sanford, NC","la":35.3637,"lo":-79.1113,"z":"27332","amt":26597,"b":"Unknown branch affiliation","v":"Olivia Machine & Tool, INC."},{"n":"The Shed Depot of Nc, LLC","o":"Small prime contractors","a":"Production","s":"Unknown sector","t":"Unknown technology","m":"Sanford, NC","la":35.4448,"lo":-79.2155,"z":"27330","amt":25000,"b":"Department of Defense Education Activity","v":"The Shed Depot of Nc, LLC"},{"n":"Spanset, INC.","o":"Small prime contractors","a":"Production","s":"Advanced Manufacturing & Machine Tools","t":"Advanced Materials and Critical Minerals","m":"Sanford, NC","la":35.4446,"lo":-79.1442,"z":"27332","amt":14301,"b":"Defense Logistics Agency","v":"Spanset, INC."},{"n":"Central Electric Membership CORP","o":"Other big prime contractors","a":"Logistics & Sustainment","s":"Power Systems & Grid Infrastructure","t":"Unknown technology","m":"Sanford, NC","la":35.4466,"lo":-79.1336,"z":"27332","amt":5401,"b":"Army","v":"Central Electric Membership CORP"}]
