[{"n":"South Carolina State University","o":"Universities","a":"Workforce training","s":"Unknown sector","t":"Unknown technology","m":"Orangeburg, SC","la":null,"lo":null,"z":"29115","amt":229550,"b":"Army","v":"South Carolina State University"},{"n":"Claflin University","o":"Universities","a":"Innovation","s":"Engineering & Technical Services","t":"Unknown technology","m":"Orangeburg, SC","la":33.483,"lo":-80.8536,"z":"29115","amt":205298,"b":"Army","v":"Claflin University"},{"n":"Staller Enterprises INC","o":"Small prime contractors","a":"Production","s":"Aircraft & Aviation","t":"Unknown technology","m":"Orangeburg, SC","la":33.403,"lo":-80.3162,"z":"29048","amt":31886,"b":"Army","v":"Staller Enterprises INC"},{"n":"JBC NORTH FIELD SBML","o":"Military Bases","a":"Logistics & Sustainment","s":"Unknown sector","t":"Unknown technology","m":"Orangeburg, SC","la":33.6326,"lo":-81.1013,"z":"29112","amt":0,"b":"Air Force","v":"JBC NORTH FIELD SBML"},{"n":"SSG Anthony O Thompson ARC","o":"Military Bases","a":"Logistics & Sustainment","s":"Unknown sector","t":"Unknown technology","m":"Orangeburg, SC","la":33.4863,"lo":-80.8739,"z":"29115","amt":0,"b":"Army Reserve","v":"SSG Anthony O Thompson ARC"}]
