[{"n":"Air Transport International INC","o":"Small prime contractors","a":"Logistics & Sustainment","s":"Maintenance, Repair & Operations","t":"Unknown technology","m":"Wilmington, OH","la":39.4364,"lo":-83.783,"z":"45177","amt":94830233,"b":"USTRANSCOM","v":"Air Transport International INC"},{"n":"Abx Air, INC.","o":"Small prime contractors","a":"Logistics & Sustainment","s":"Unknown sector","t":"Unknown technology","m":"Wilmington, OH","la":39.4364,"lo":-83.783,"z":"45177","amt":1966917,"b":"USTRANSCOM","v":"Abx Air, INC."},{"n":"Oasis Aviation Services, LLC","o":"Subcontractors","a":"Services","s":"Unknown sector","t":"Unknown technology","m":"Wilmington, OH","la":39.4027,"lo":-83.7555,"z":"45177","amt":1547119,"b":"Unknown branch affiliation","v":"Oasis Aviation Services, LLC"},{"n":"Oasis Aviation Services, LLC","o":"Subcontractors","a":"Services","s":"Unknown sector","t":"Unknown technology","m":"Wilmington, OH","la":39.4874,"lo":-83.7177,"z":"45169","amt":906651,"b":"Unknown branch affiliation","v":"Oasis Aviation Services, LLC"},{"n":"Airborne Maintenance and Engineering Services, INC","o":"Subcontractors","a":"Services","s":"Unknown sector","t":"Unknown technology","m":"Wilmington, OH","la":39.4364,"lo":-83.783,"z":"45177","amt":100000,"b":"Unknown branch affiliation","v":"Airborne Maintenance and Engineering Services, INC"},{"n":"Csa Service Solutions, LLC","o":"Other big prime contractors","a":"Logistics & Sustainment","s":"Maintenance, Repair & Operations","t":"Unknown technology","m":"Wilmington, OH","la":39.4344,"lo":-83.7991,"z":"45177","amt":15410,"b":"Army","v":"Csa Service Solutions, LLC"}]
