[{"m":"Washington-Arlington-Alexandria, DC-VA-MD-WV","total_assets":5802,"total_amount":65825478862,"total_fmt":"$65.8B","rank":1},{"m":"Dallas-Fort Worth-Arlington, TX","total_assets":1391,"total_amount":44035786181,"total_fmt":"$44B","rank":2},{"m":"Unassigned","total_assets":9347,"total_amount":24764562491,"total_fmt":"$24.8B","rank":3},{"m":"Los Angeles-Long Beach-Anaheim, CA","total_assets":2769,"total_amount":18217328758,"total_fmt":"$18.2B","rank":4},{"m":"Boston-Cambridge-Newton, MA-NH","total_assets":1744,"total_amount":17531055952,"total_fmt":"$17.5B","rank":5},{"m":"Norwich-New London-Willimantic, CT","total_assets":65,"total_amount":15528570380,"total_fmt":"$15.5B","rank":6},{"m":"Virginia Beach-Chesapeake-Norfolk, VA-NC","total_assets":1228,"total_amount":15476869782,"total_fmt":"$15.5B","rank":7},{"m":"Philadelphia-Camden-Wilmington, PA-NJ-DE-MD","total_assets":1406,"total_amount":15282565680,"total_fmt":"$15.3B","rank":8},{"m":"Tucson, AZ","total_assets":248,"total_amount":13098624550,"total_fmt":"$13.1B","rank":9},{"m":"St. Louis, MO-IL","total_assets":467,"total_amount":12323356796,"total_fmt":"$12.3B","rank":10},{"m":"San Diego-Chula Vista-Carlsbad, CA","total_assets":1683,"total_amount":11908319981,"total_fmt":"$11.9B","rank":11},{"m":"Huntsville, AL","total_assets":613,"total_amount":9980813691,"total_fmt":"$10B","rank":12},{"m":"Baltimore-Columbia-Towson, MD","total_assets":1397,"total_amount":9034138198,"total_fmt":"$9B","rank":13},{"m":"Orlando-Kissimmee-Sanford, FL","total_assets":539,"total_amount":8471291719,"total_fmt":"$8.5B","rank":14},{"m":"New York-Newark-Jersey City, NY-NJ","total_assets":2558,"total_amount":8235174604,"total_fmt":"$8.2B","rank":15},{"m":"Louisville-Jefferson County, KY-IN","total_assets":172,"total_amount":7970404241,"total_fmt":"$8B","rank":16},{"m":"Seattle-Tacoma-Bellevue, WA","total_assets":943,"total_amount":7836667491,"total_fmt":"$7.8B","rank":17},{"m":"Denver-Aurora-Centennial, CO","total_assets":780,"total_amount":7460125695,"total_fmt":"$7.5B","rank":18},{"m":"Hartford-West Hartford-East Hartford, CT","total_assets":227,"total_amount":7199046523,"total_fmt":"$7.2B","rank":19},{"m":"Chicago-Naperville-Elgin, IL-IN","total_assets":1214,"total_amount":6898148046,"total_fmt":"$6.9B","rank":20},{"m":"Phoenix-Mesa-Chandler, AZ","total_assets":865,"total_amount":6869523489,"total_fmt":"$6.9B","rank":21},{"m":"Palm Bay-Melbourne-Titusville, FL","total_assets":317,"total_amount":5999352486,"total_fmt":"$6B","rank":22},{"m":"Houston-Pasadena-The Woodlands, TX","total_assets":961,"total_amount":5465268056,"total_fmt":"$5.5B","rank":23},{"m":"Bridgeport-Stamford-Danbury, CT","total_assets":127,"total_amount":5455809150,"total_fmt":"$5.5B","rank":24},{"m":"Atlanta-Sandy Springs-Roswell, GA","total_assets":1244,"total_amount":5257413951,"total_fmt":"$5.3B","rank":25},{"m":"Gulfport-Biloxi, MS","total_assets":129,"total_amount":5079421129,"total_fmt":"$5.1B","rank":26},{"m":"Detroit-Warren-Dearborn, MI","total_assets":695,"total_amount":4794287293,"total_fmt":"$4.8B","rank":27},{"m":"Anchorage, AK","total_assets":578,"total_amount":4466305734,"total_fmt":"$4.5B","rank":28},{"m":"Miami-Fort Lauderdale-West Palm Beach, FL","total_assets":1008,"total_amount":4251604361,"total_fmt":"$4.3B","rank":29},{"m":"Colorado Springs, CO","total_assets":445,"total_amount":4154482494,"total_fmt":"$4.2B","rank":30},{"m":"Tampa-St. Petersburg-Clearwater, FL","total_assets":675,"total_amount":4027257279,"total_fmt":"$4B","rank":31},{"m":"Austin-Round Rock-San Marcos, TX","total_assets":537,"total_amount":3939592932,"total_fmt":"$3.9B","rank":32},{"m":"San Francisco-Oakland-Fremont, CA","total_assets":907,"total_amount":3869083198,"total_fmt":"$3.9B","rank":33},{"m":"San Antonio-New Braunfels, TX","total_assets":708,"total_amount":3780734768,"total_fmt":"$3.8B","rank":34},{"m":"Sacramento-Roseville-Folsom, CA","total_assets":368,"total_amount":3712253840,"total_fmt":"$3.7B","rank":35},{"m":"Urban Honolulu, HI","total_assets":573,"total_amount":3590835280,"total_fmt":"$3.6B","rank":36},{"m":"Pittsburgh, PA","total_assets":522,"total_amount":3579881991,"total_fmt":"$3.6B","rank":37},{"m":"Manchester-Nashua, NH","total_assets":154,"total_amount":3521441743,"total_fmt":"$3.5B","rank":38},{"m":"Oklahoma City, OK","total_assets":359,"total_amount":3272669910,"total_fmt":"$3.3B","rank":39},{"m":"Ogden, UT","total_assets":181,"total_amount":3091102807,"total_fmt":"$3.1B","rank":40},{"m":"San Jose-Sunnyvale-Santa Clara, CA","total_assets":553,"total_amount":2866662714,"total_fmt":"$2.9B","rank":41},{"m":"Portland-South Portland, ME","total_assets":121,"total_amount":2799853901,"total_fmt":"$2.8B","rank":42},{"m":"Dayton-Kettering-Beavercreek, OH","total_assets":425,"total_amount":2781252077,"total_fmt":"$2.8B","rank":43},{"m":"Lexington Park, MD","total_assets":151,"total_amount":2566360205,"total_fmt":"$2.6B","rank":44},{"m":"Cincinnati, OH-KY-IN","total_assets":372,"total_amount":2532610646,"total_fmt":"$2.5B","rank":45},{"m":"York-Hanover, PA","total_assets":114,"total_amount":2501508200,"total_fmt":"$2.5B","rank":46},{"m":"Syracuse, NY","total_assets":143,"total_amount":2364353544,"total_fmt":"$2.4B","rank":47},{"m":"Kansas City, MO-KS","total_assets":451,"total_amount":2353778247,"total_fmt":"$2.4B","rank":48},{"m":"Minneapolis-St. Paul-Bloomington, MN-WI","total_assets":650,"total_amount":2306278862,"total_fmt":"$2.3B","rank":49},{"m":"Indianapolis-Carmel-Greenwood, IN","total_assets":337,"total_amount":2300686651,"total_fmt":"$2.3B","rank":50},{"m":"Jacksonville, FL","total_assets":472,"total_amount":2265930149,"total_fmt":"$2.3B","rank":51},{"m":"Rochester, NY","total_assets":239,"total_amount":2258270383,"total_fmt":"$2.3B","rank":52},{"m":"Greenville-Anderson-Greer, SC","total_assets":141,"total_amount":2124892546,"total_fmt":"$2.1B","rank":53},{"m":"Cedar Rapids, IA","total_assets":42,"total_amount":1986916955,"total_fmt":"$2B","rank":54},{"m":"Binghamton, NY","total_assets":50,"total_amount":1798365094,"total_fmt":"$1.8B","rank":55},{"m":"Portland-Vancouver-Hillsboro, OR-WA","total_assets":448,"total_amount":1697173226,"total_fmt":"$1.7B","rank":56},{"m":"Oshkosh-Neenah, WI","total_assets":41,"total_amount":1603679091,"total_fmt":"$1.6B","rank":57},{"m":"Jackson, MS","total_assets":99,"total_amount":1564542003,"total_fmt":"$1.6B","rank":58},{"m":"Columbus, OH","total_assets":373,"total_amount":1478627872,"total_fmt":"$1.5B","rank":59},{"m":"Tulsa, OK","total_assets":265,"total_amount":1476533290,"total_fmt":"$1.5B","rank":60},{"m":"South Bend-Mishawaka, IN-MI","total_assets":42,"total_amount":1333424509,"total_fmt":"$1.3B","rank":61},{"m":"Crestview-Fort Walton Beach-Destin, FL","total_assets":173,"total_amount":1258128347,"total_fmt":"$1.3B","rank":62},{"m":"Ann Arbor, MI","total_assets":101,"total_amount":1188025015,"total_fmt":"$1.2B","rank":63},{"m":"New Orleans-Metairie, LA","total_assets":235,"total_amount":1186332968,"total_fmt":"$1.2B","rank":64},{"m":"Amarillo, TX","total_assets":14,"total_amount":1148761007,"total_fmt":"$1.1B","rank":65},{"m":"Charleston-North Charleston, SC","total_assets":280,"total_amount":1133515850,"total_fmt":"$1.1B","rank":66},{"m":"Salt Lake City-Murray, UT","total_assets":347,"total_amount":1044799376,"total_fmt":"$1B","rank":67},{"m":"Riverside-San Bernardino-Ontario, CA","total_assets":575,"total_amount":1032148130,"total_fmt":"$1B","rank":68},{"m":"Lexington-Fayette, KY","total_assets":93,"total_amount":1019975020,"total_fmt":"$1B","rank":69},{"m":"Milwaukee-Waukesha, WI","total_assets":359,"total_amount":1014177821,"total_fmt":"$1B","rank":70},{"m":"Birmingham, AL","total_assets":188,"total_amount":1001929067,"total_fmt":"$1B","rank":71},{"m":"Las Vegas-Henderson-North Las Vegas, NV","total_assets":280,"total_amount":996453184,"total_fmt":"$996M","rank":72},{"m":"Albuquerque, NM","total_assets":312,"total_amount":981905180,"total_fmt":"$982M","rank":73},{"m":"Memphis, TN-MS-AR","total_assets":134,"total_amount":959050966,"total_fmt":"$959M","rank":74},{"m":"Oxnard-Thousand Oaks-Ventura, CA","total_assets":327,"total_amount":957895608,"total_fmt":"$958M","rank":75},{"m":"Mobile, AL","total_assets":85,"total_amount":916007594,"total_fmt":"$916M","rank":76},{"m":"Omaha, NE-IA","total_assets":168,"total_amount":893274127,"total_fmt":"$893M","rank":77},{"m":"Wichita, KS","total_assets":162,"total_amount":871911831,"total_fmt":"$872M","rank":78},{"m":"Columbia, SC","total_assets":142,"total_amount":861987859,"total_fmt":"$862M","rank":79},{"m":"Scranton--Wilkes-Barre, PA","total_assets":96,"total_amount":854439520,"total_fmt":"$854M","rank":80},{"m":"Richmond, VA","total_assets":332,"total_amount":818764407,"total_fmt":"$819M","rank":81},{"m":"Reno, NV","total_assets":96,"total_amount":778425555,"total_fmt":"$778M","rank":82},{"m":"Tullahoma-Manchester, TN","total_assets":15,"total_amount":770343791,"total_fmt":"$770M","rank":83},{"m":"Rockford, IL","total_assets":36,"total_amount":768776719,"total_fmt":"$769M","rank":84},{"m":"Charlotte-Concord-Gastonia, NC-SC","total_assets":399,"total_amount":729158778,"total_fmt":"$729M","rank":85},{"m":"Buffalo-Cheektowaga, NY","total_assets":216,"total_amount":709020029,"total_fmt":"$709M","rank":86},{"m":"Baton Rouge, LA","total_assets":117,"total_amount":690807319,"total_fmt":"$691M","rank":87},{"m":"Marinette, WI-MI","total_assets":7,"total_amount":652860139,"total_fmt":"$653M","rank":88},{"m":"Burlington-South Burlington, VT","total_assets":64,"total_amount":642250282,"total_fmt":"$642M","rank":89},{"m":"Bremerton-Silverdale-Port Orchard, WA","total_assets":153,"total_amount":638006386,"total_fmt":"$638M","rank":90},{"m":"Blacksburg-Christiansburg-Radford, VA","total_assets":43,"total_amount":626990327,"total_fmt":"$627M","rank":91},{"m":"Providence-Warwick, RI-MA","total_assets":374,"total_amount":621765030,"total_fmt":"$622M","rank":92},{"m":"Santa Maria-Santa Barbara, CA","total_assets":180,"total_amount":588832973,"total_fmt":"$589M","rank":93},{"m":"Slidell-Mandeville-Covington, LA","total_assets":53,"total_amount":578893743,"total_fmt":"$579M","rank":94},{"m":"College Station-Bryan, TX","total_assets":54,"total_amount":570585276,"total_fmt":"$571M","rank":95},{"m":"Cleveland, OH","total_assets":422,"total_amount":552513338,"total_fmt":"$553M","rank":96},{"m":"Harrisburg-Carlisle, PA","total_assets":151,"total_amount":540219940,"total_fmt":"$540M","rank":97},{"m":"Janesville-Beloit, WI","total_assets":15,"total_amount":530113287,"total_fmt":"$530M","rank":98},{"m":"Durham-Chapel Hill, NC","total_assets":109,"total_amount":514330565,"total_fmt":"$514M","rank":99},{"m":"Findlay, OH","total_assets":5,"total_amount":480181186,"total_fmt":"$480M","rank":100},{"m":"Pensacola-Ferry Pass-Brent, FL","total_assets":203,"total_amount":460727780,"total_fmt":"$461M","rank":101},{"m":"Nashville-Davidson--Murfreesboro--Franklin, TN","total_assets":243,"total_amount":459753720,"total_fmt":"$460M","rank":102},{"m":"Raleigh-Cary, NC","total_assets":316,"total_amount":458476824,"total_fmt":"$458M","rank":103},{"m":"Fort Wayne, IN","total_assets":73,"total_amount":455204418,"total_fmt":"$455M","rank":104},{"m":"Knoxville, TN","total_assets":195,"total_amount":448340705,"total_fmt":"$448M","rank":105},{"m":"Augusta-Richmond County, GA-SC","total_assets":99,"total_amount":442918857,"total_fmt":"$443M","rank":106},{"m":"Clarksville, TN-KY","total_assets":53,"total_amount":438593485,"total_fmt":"$439M","rank":107},{"m":"Utica-Rome, NY","total_assets":111,"total_amount":427389845,"total_fmt":"$427M","rank":108},{"m":"Burlington, IA-IL","total_assets":13,"total_amount":421030492,"total_fmt":"$421M","rank":109},{"m":"Pittsfield, MA","total_assets":18,"total_amount":404011659,"total_fmt":"$404M","rank":110},{"m":"Lansing-East Lansing, MI","total_assets":40,"total_amount":394582728,"total_fmt":"$395M","rank":111},{"m":"Montgomery, AL","total_assets":142,"total_amount":393187638,"total_fmt":"$393M","rank":112},{"m":"Richmond-Berea, KY","total_assets":18,"total_amount":389646243,"total_fmt":"$390M","rank":113},{"m":"Fort Collins-Loveland, CO","total_assets":78,"total_amount":385221016,"total_fmt":"$385M","rank":114},{"m":"State College, PA","total_assets":48,"total_amount":380543382,"total_fmt":"$381M","rank":115},{"m":"Muskegon-Norton Shores, MI","total_assets":26,"total_amount":377501149,"total_fmt":"$378M","rank":116},{"m":"Waco, TX","total_assets":33,"total_amount":362616096,"total_fmt":"$363M","rank":117},{"m":"El Paso, TX","total_assets":157,"total_amount":359104270,"total_fmt":"$359M","rank":118},{"m":"Roanoke, VA","total_assets":47,"total_amount":355074905,"total_fmt":"$355M","rank":119},{"m":"Cumberland, MD-WV","total_assets":17,"total_amount":353883617,"total_fmt":"$354M","rank":120},{"m":"Boise City, ID","total_assets":150,"total_amount":345743931,"total_fmt":"$346M","rank":121},{"m":"Johnstown, PA","total_assets":24,"total_amount":340555437,"total_fmt":"$341M","rank":122},{"m":"Houma-Bayou Cane-Thibodaux, LA","total_assets":57,"total_amount":339561208,"total_fmt":"$340M","rank":123},{"m":"San Juan-Bayamon-Caguas, PR","total_assets":156,"total_amount":331348022,"total_fmt":"$331M","rank":124},{"m":"Boulder, CO","total_assets":168,"total_amount":326913101,"total_fmt":"$327M","rank":125},{"m":"Warner Robins, GA","total_assets":89,"total_amount":317538808,"total_fmt":"$318M","rank":126},{"m":"Bozeman, MT","total_assets":45,"total_amount":315190154,"total_fmt":"$315M","rank":127},{"m":"Savannah, GA","total_assets":78,"total_amount":313779299,"total_fmt":"$314M","rank":128},{"m":"Worcester, MA","total_assets":187,"total_amount":305566616,"total_fmt":"$306M","rank":129},{"m":"Madison, WI","total_assets":120,"total_amount":303811194,"total_fmt":"$304M","rank":130},{"m":"Charlottesville, VA","total_assets":64,"total_amount":297767962,"total_fmt":"$298M","rank":131},{"m":"Albany-Schenectady-Troy, NY","total_assets":185,"total_amount":291386417,"total_fmt":"$291M","rank":132},{"m":"Evansville, IN","total_assets":31,"total_amount":289700753,"total_fmt":"$290M","rank":133},{"m":"Sioux City, IA-NE-SD","total_assets":23,"total_amount":284374117,"total_fmt":"$284M","rank":134},{"m":"Brattleboro, VT","total_assets":12,"total_amount":270302968,"total_fmt":"$270M","rank":135},{"m":"Las Cruces, NM","total_assets":38,"total_amount":268190036,"total_fmt":"$268M","rank":136},{"m":"Santa Cruz-Watsonville, CA","total_assets":42,"total_amount":266733740,"total_fmt":"$267M","rank":137},{"m":"Deltona-Daytona Beach-Ormond Beach, FL","total_assets":83,"total_amount":255379022,"total_fmt":"$255M","rank":138},{"m":"Marion-Herrin, IL","total_assets":7,"total_amount":252295875,"total_fmt":"$252M","rank":139},{"m":"Panama City-Panama City Beach, FL","total_assets":94,"total_amount":248955079,"total_fmt":"$249M","rank":140},{"m":"Brunswick-St. Simons, GA","total_assets":16,"total_amount":247523822,"total_fmt":"$248M","rank":141},{"m":"Logan, UT-ID","total_assets":39,"total_amount":246187287,"total_fmt":"$246M","rank":142},{"m":"Kingsport-Bristol, TN-VA","total_assets":18,"total_amount":241190981,"total_fmt":"$241M","rank":143},{"m":"Kenosha, WI","total_assets":15,"total_amount":238992799,"total_fmt":"$239M","rank":144},{"m":"Fairbanks-College, AK","total_assets":101,"total_amount":236645324,"total_fmt":"$237M","rank":145},{"m":"Reading, PA","total_assets":59,"total_amount":231403125,"total_fmt":"$231M","rank":146},{"m":"Grand Rapids-Wyoming-Kentwood, MI","total_assets":154,"total_amount":225969379,"total_fmt":"$226M","rank":147},{"m":"Mayaguez, PR","total_assets":15,"total_amount":218326415,"total_fmt":"$218M","rank":148},{"m":"Stockton-Lodi, CA","total_assets":43,"total_amount":211202295,"total_fmt":"$211M","rank":149},{"m":"Tallahassee, FL","total_assets":62,"total_amount":191435390,"total_fmt":"$191M","rank":150},{"m":"Fayetteville, NC","total_assets":108,"total_amount":190862938,"total_fmt":"$191M","rank":151},{"m":"Cape Coral-Fort Myers, FL","total_assets":67,"total_amount":189330764,"total_fmt":"$189M","rank":152},{"m":"Jefferson City, MO","total_assets":20,"total_amount":187657155,"total_fmt":"$188M","rank":153},{"m":"Davenport-Moline-Rock Island, IA-IL","total_assets":101,"total_amount":183637936,"total_fmt":"$184M","rank":154},{"m":"Trenton-Princeton, NJ","total_assets":89,"total_amount":181666888,"total_fmt":"$182M","rank":155},{"m":"Spokane-Spokane Valley, WA","total_assets":106,"total_amount":181271186,"total_fmt":"$181M","rank":156},{"m":"Lebanon-Claremont, NH-VT","total_assets":65,"total_amount":179903693,"total_fmt":"$180M","rank":157},{"m":"Greensboro-High Point, NC","total_assets":128,"total_amount":176849926,"total_fmt":"$177M","rank":158},{"m":"Killeen-Temple, TX","total_assets":80,"total_amount":165023818,"total_fmt":"$165M","rank":159},{"m":"Little Rock-North Little Rock-Conway, AR","total_assets":160,"total_amount":164648893,"total_fmt":"$165M","rank":160},{"m":"La Crosse-Onalaska, WI-MN","total_assets":45,"total_amount":161959768,"total_fmt":"$162M","rank":161},{"m":"Allentown-Bethlehem-Easton, PA-NJ","total_assets":130,"total_amount":160019668,"total_fmt":"$160M","rank":162},{"m":"Champaign-Urbana, IL","total_assets":44,"total_amount":156839598,"total_fmt":"$157M","rank":163},{"m":"Texarkana, TX-AR","total_assets":45,"total_amount":155912776,"total_fmt":"$156M","rank":164},{"m":"Akron, OH","total_assets":138,"total_amount":155754228,"total_fmt":"$156M","rank":165},{"m":"Lebanon, PA","total_assets":13,"total_amount":144929277,"total_fmt":"$145M","rank":166},{"m":"San Luis Obispo-Paso Robles, CA","total_assets":73,"total_amount":143635272,"total_fmt":"$144M","rank":167},{"m":"Oak Harbor, WA","total_assets":21,"total_amount":142370772,"total_fmt":"$142M","rank":168},{"m":"Bakersfield-Delano, CA","total_assets":86,"total_amount":142171229,"total_fmt":"$142M","rank":169},{"m":"Salem, OR","total_assets":31,"total_amount":137687785,"total_fmt":"$138M","rank":170},{"m":"Bloomington, IN","total_assets":39,"total_amount":134153025,"total_fmt":"$134M","rank":171},{"m":"Asheville, NC","total_assets":47,"total_amount":134122517,"total_fmt":"$134M","rank":172},{"m":"Columbus, IN","total_assets":8,"total_amount":133812744,"total_fmt":"$134M","rank":173},{"m":"Greeley, CO","total_assets":33,"total_amount":133346865,"total_fmt":"$133M","rank":174},{"m":"Jacksonville, NC","total_assets":55,"total_amount":130183751,"total_fmt":"$130M","rank":175},{"m":"Lawton, OK","total_assets":50,"total_amount":126535564,"total_fmt":"$127M","rank":176},{"m":"Barnstable Town, MA","total_assets":51,"total_amount":122937366,"total_fmt":"$123M","rank":177},{"m":"North Port-Bradenton-Sarasota, FL","total_assets":108,"total_amount":119156712,"total_fmt":"$119M","rank":178},{"m":"New Bern, NC","total_assets":48,"total_amount":119091005,"total_fmt":"$119M","rank":179},{"m":"Napa, CA","total_assets":11,"total_amount":118795944,"total_fmt":"$119M","rank":180},{"m":"Amherst Town-Northampton, MA","total_assets":31,"total_amount":118130115,"total_fmt":"$118M","rank":181},{"m":"Idaho Falls, ID","total_assets":28,"total_amount":117364230,"total_fmt":"$117M","rank":182},{"m":"Anderson Creek, NC","total_assets":37,"total_amount":116528384,"total_fmt":"$117M","rank":183},{"m":"Lake Charles, LA","total_assets":17,"total_amount":115657009,"total_fmt":"$116M","rank":184},{"m":"Corbin, KY","total_assets":13,"total_amount":115016148,"total_fmt":"$115M","rank":185},{"m":"Juneau, AK","total_assets":14,"total_amount":113337937,"total_fmt":"$113M","rank":186},{"m":"Provo-Orem-Lehi, UT","total_assets":86,"total_amount":112925369,"total_fmt":"$113M","rank":187},{"m":"Des Moines-West Des Moines, IA","total_assets":84,"total_amount":110477730,"total_fmt":"$110M","rank":188},{"m":"Greenwood, MS","total_assets":7,"total_amount":109378278,"total_fmt":"$109M","rank":189},{"m":"Morgan City, LA","total_assets":10,"total_amount":107710431,"total_fmt":"$108M","rank":190},{"m":"Sierra Vista-Douglas, AZ","total_assets":43,"total_amount":107310460,"total_fmt":"$107M","rank":191},{"m":"Indiana, PA","total_assets":13,"total_amount":106664722,"total_fmt":"$107M","rank":192},{"m":"New Haven, CT","total_assets":96,"total_amount":104286475,"total_fmt":"$104M","rank":193},{"m":"Peoria, IL","total_assets":48,"total_amount":104075091,"total_fmt":"$104M","rank":194},{"m":"Talladega-Sylacauga, AL","total_assets":17,"total_amount":104049269,"total_fmt":"$104M","rank":195},{"m":"Canton-Massillon, OH","total_assets":33,"total_amount":103817655,"total_fmt":"$104M","rank":196},{"m":"Naples-Marco Island, FL","total_assets":38,"total_amount":101521486,"total_fmt":"$102M","rank":197},{"m":"Wilmington, OH","total_assets":6,"total_amount":99366330,"total_fmt":"$99M","rank":198},{"m":"Topeka, KS","total_assets":63,"total_amount":97359302,"total_fmt":"$97M","rank":199},{"m":"Laconia, NH","total_assets":12,"total_amount":95850487,"total_fmt":"$96M","rank":200},{"m":"Oxford, MS","total_assets":5,"total_amount":95206784,"total_fmt":"$95M","rank":201},{"m":"Erie, PA","total_assets":46,"total_amount":94452710,"total_fmt":"$94M","rank":202},{"m":"Kahului-Wailuku, HI","total_assets":21,"total_amount":92318790,"total_fmt":"$92M","rank":203},{"m":"Columbus, GA-AL","total_assets":52,"total_amount":91469790,"total_fmt":"$91M","rank":204},{"m":"Valdosta, GA","total_assets":36,"total_amount":90250266,"total_fmt":"$90M","rank":205},{"m":"Bangor, ME","total_assets":30,"total_amount":90190715,"total_fmt":"$90M","rank":206},{"m":"Dyersburg, TN","total_assets":5,"total_amount":89715836,"total_fmt":"$90M","rank":207},{"m":"Wilmington, NC","total_assets":110,"total_amount":89660710,"total_fmt":"$90M","rank":208},{"m":"Enterprise, AL","total_assets":30,"total_amount":88260187,"total_fmt":"$88M","rank":209},{"m":"Lincoln, NE","total_assets":50,"total_amount":87971755,"total_fmt":"$88M","rank":210},{"m":"Longview-Kelso, WA","total_assets":22,"total_amount":87424476,"total_fmt":"$87M","rank":211},{"m":"McAllen-Edinburg-Mission, TX","total_assets":24,"total_amount":86999787,"total_fmt":"$87M","rank":212},{"m":"Cadillac, MI","total_assets":6,"total_amount":86850204,"total_fmt":"$87M","rank":213},{"m":"Gainesville, FL","total_assets":59,"total_amount":86122082,"total_fmt":"$86M","rank":214},{"m":"Wichita Falls, TX","total_assets":34,"total_amount":84872709,"total_fmt":"$85M","rank":215},{"m":"Charleston, WV","total_assets":22,"total_amount":83206723,"total_fmt":"$83M","rank":216},{"m":"Springfield, IL","total_assets":30,"total_amount":82479977,"total_fmt":"$82M","rank":217},{"m":"Frankfort, KY","total_assets":13,"total_amount":82396993,"total_fmt":"$82M","rank":218},{"m":"Appleton, WI","total_assets":33,"total_amount":80243024,"total_fmt":"$80M","rank":219},{"m":"Clarksburg, WV","total_assets":13,"total_amount":79863580,"total_fmt":"$80M","rank":220},{"m":"Santa Fe, NM","total_assets":26,"total_amount":79836300,"total_fmt":"$80M","rank":221},{"m":"Youngstown-Warren, OH","total_assets":64,"total_amount":79618017,"total_fmt":"$80M","rank":222},{"m":"Winston-Salem, NC","total_assets":54,"total_amount":79062229,"total_fmt":"$79M","rank":223},{"m":"Burlington, NC","total_assets":20,"total_amount":77815192,"total_fmt":"$78M","rank":224},{"m":"Daphne-Fairhope-Foley, AL","total_assets":40,"total_amount":77454607,"total_fmt":"$77M","rank":225},{"m":"Toledo, OH","total_assets":72,"total_amount":77149849,"total_fmt":"$77M","rank":226},{"m":"Helena, MT","total_assets":30,"total_amount":76988986,"total_fmt":"$77M","rank":227},{"m":"Augusta-Waterville, ME","total_assets":27,"total_amount":76674413,"total_fmt":"$77M","rank":228},{"m":"Athens-Clarke County, GA","total_assets":20,"total_amount":74778283,"total_fmt":"$75M","rank":229},{"m":"Fayetteville-Springdale-Rogers, AR","total_assets":58,"total_amount":74462241,"total_fmt":"$74M","rank":230},{"m":"Warrensburg, MO","total_assets":23,"total_amount":73912924,"total_fmt":"$74M","rank":231},{"m":"Lafayette, LA","total_assets":65,"total_amount":73365095,"total_fmt":"$73M","rank":232},{"m":"Altus, OK","total_assets":15,"total_amount":71375945,"total_fmt":"$71M","rank":233},{"m":"Cedartown, GA","total_assets":1,"total_amount":71288103,"total_fmt":"$71M","rank":234},{"m":"Rapid City, SD","total_assets":68,"total_amount":70868601,"total_fmt":"$71M","rank":235},{"m":"Grand Forks, ND-MN","total_assets":35,"total_amount":70638258,"total_fmt":"$71M","rank":236},{"m":"Elizabethtown, KY","total_assets":20,"total_amount":70346697,"total_fmt":"$70M","rank":237},{"m":"Sioux Falls, SD-MN","total_assets":45,"total_amount":70027234,"total_fmt":"$70M","rank":238},{"m":"Lafayette-West Lafayette, IN","total_assets":32,"total_amount":69066509,"total_fmt":"$69M","rank":239},{"m":"Springfield, MO","total_assets":76,"total_amount":68916738,"total_fmt":"$69M","rank":240},{"m":"Joplin, MO-KS","total_assets":22,"total_amount":68679238,"total_fmt":"$69M","rank":241},{"m":"Hilton Head Island-Bluffton-Port Royal, SC","total_assets":41,"total_amount":67966543,"total_fmt":"$68M","rank":242},{"m":"Chambersburg, PA","total_assets":38,"total_amount":67431909,"total_fmt":"$67M","rank":243},{"m":"Port St. Lucie, FL","total_assets":59,"total_amount":67137358,"total_fmt":"$67M","rank":244},{"m":"Vallejo, CA","total_assets":71,"total_amount":65996185,"total_fmt":"$66M","rank":245},{"m":"Pinehurst-Southern Pines, NC","total_assets":39,"total_amount":65877365,"total_fmt":"$66M","rank":246},{"m":"Lakeland-Winter Haven, FL","total_assets":37,"total_amount":65667623,"total_fmt":"$66M","rank":247},{"m":"Morgantown, WV","total_assets":23,"total_amount":64935195,"total_fmt":"$65M","rank":248},{"m":"Visalia, CA","total_assets":21,"total_amount":64585309,"total_fmt":"$65M","rank":249},{"m":"Pine Bluff, AR","total_assets":14,"total_amount":64141115,"total_fmt":"$64M","rank":250},{"m":"Greenville, NC","total_assets":13,"total_amount":62969884,"total_fmt":"$63M","rank":251},{"m":"Shreveport-Bossier City, LA","total_assets":92,"total_amount":62437494,"total_fmt":"$62M","rank":252},{"m":"St. George, UT","total_assets":30,"total_amount":62056041,"total_fmt":"$62M","rank":253},{"m":"Arecibo, PR","total_assets":4,"total_amount":61681087,"total_fmt":"$62M","rank":254},{"m":"Lancaster, PA","total_assets":65,"total_amount":61414753,"total_fmt":"$61M","rank":255},{"m":"Yuma, AZ","total_assets":45,"total_amount":60691042,"total_fmt":"$61M","rank":256},{"m":"Lynchburg, VA","total_assets":36,"total_amount":60642090,"total_fmt":"$61M","rank":257},{"m":"Houghton, MI","total_assets":14,"total_amount":59528644,"total_fmt":"$60M","rank":258},{"m":"Corpus Christi, TX","total_assets":52,"total_amount":59314703,"total_fmt":"$59M","rank":259},{"m":"Kalamazoo-Portage, MI","total_assets":33,"total_amount":58620787,"total_fmt":"$59M","rank":260},{"m":"Coeur d'Alene, ID","total_assets":47,"total_amount":57738137,"total_fmt":"$58M","rank":261},{"m":"Shelton, WA","total_assets":8,"total_amount":57562029,"total_fmt":"$58M","rank":262},{"m":"Williamsport, PA","total_assets":23,"total_amount":56577154,"total_fmt":"$57M","rank":263},{"m":"Chico, CA","total_assets":24,"total_amount":55731095,"total_fmt":"$56M","rank":264},{"m":"Elkhart-Goshen, IN","total_assets":26,"total_amount":55720971,"total_fmt":"$56M","rank":265},{"m":"Morehead City, NC","total_assets":29,"total_amount":53983468,"total_fmt":"$54M","rank":266},{"m":"Ithaca, NY","total_assets":27,"total_amount":53402239,"total_fmt":"$53M","rank":267},{"m":"Spartanburg, SC","total_assets":45,"total_amount":51569978,"total_fmt":"$52M","rank":268},{"m":"Huntington-Ashland, WV-KY-OH","total_assets":33,"total_amount":50115433,"total_fmt":"$50M","rank":269},{"m":"Kennewick-Richland, WA","total_assets":48,"total_amount":49924134,"total_fmt":"$50M","rank":270},{"m":"Fargo, ND-MN","total_assets":82,"total_amount":49363406,"total_fmt":"$49M","rank":271},{"m":"Auburn-Opelika, AL","total_assets":33,"total_amount":49171449,"total_fmt":"$49M","rank":272},{"m":"Heber, UT","total_assets":17,"total_amount":49068541,"total_fmt":"$49M","rank":273},{"m":"Carson City, NV","total_assets":25,"total_amount":48436158,"total_fmt":"$48M","rank":274},{"m":"Selma, AL","total_assets":7,"total_amount":48274642,"total_fmt":"$48M","rank":275},{"m":"Salinas, CA","total_assets":52,"total_amount":48231990,"total_fmt":"$48M","rank":276},{"m":"Brigham City, UT-ID","total_assets":14,"total_amount":47948469,"total_fmt":"$48M","rank":277},{"m":"Mount Vernon-Anacortes, WA","total_assets":33,"total_amount":47861074,"total_fmt":"$48M","rank":278},{"m":"Pueblo, CO","total_assets":20,"total_amount":47056246,"total_fmt":"$47M","rank":279},{"m":"Cheyenne, WY","total_assets":54,"total_amount":46777512,"total_fmt":"$47M","rank":280},{"m":"Great Falls, MT","total_assets":57,"total_amount":46424055,"total_fmt":"$46M","rank":281},{"m":"New Iberia, LA","total_assets":18,"total_amount":46270610,"total_fmt":"$46M","rank":282},{"m":"Jamestown-Dunkirk, NY","total_assets":15,"total_amount":46259758,"total_fmt":"$46M","rank":283},{"m":"Columbus, MS","total_assets":24,"total_amount":46209123,"total_fmt":"$46M","rank":284},{"m":"Waterbury-Shelton, CT","total_assets":52,"total_amount":45986247,"total_fmt":"$46M","rank":285},{"m":"Springfield, MA","total_assets":103,"total_amount":45578061,"total_fmt":"$46M","rank":286},{"m":"Douglas, GA","total_assets":4,"total_amount":45074204,"total_fmt":"$45M","rank":287},{"m":"Ocala, FL","total_assets":30,"total_amount":44751792,"total_fmt":"$45M","rank":288},{"m":"Beaumont-Port Arthur, TX","total_assets":27,"total_amount":43772522,"total_fmt":"$44M","rank":289},{"m":"Fort Leonard Wood, MO","total_assets":25,"total_amount":43621853,"total_fmt":"$44M","rank":290},{"m":"Manhattan, KS","total_assets":37,"total_amount":43003676,"total_fmt":"$43M","rank":291},{"m":"Harrisonburg, VA","total_assets":14,"total_amount":42106358,"total_fmt":"$42M","rank":292},{"m":"Macon-Bibb County, GA","total_assets":56,"total_amount":42002090,"total_fmt":"$42M","rank":293},{"m":"Vineland, NJ","total_assets":10,"total_amount":41710100,"total_fmt":"$42M","rank":294},{"m":"Anniston-Oxford, AL","total_assets":47,"total_amount":41163456,"total_fmt":"$41M","rank":295},{"m":"Eugene-Springfield, OR","total_assets":54,"total_amount":40918264,"total_fmt":"$41M","rank":296},{"m":"Minot, ND","total_assets":40,"total_amount":40212260,"total_fmt":"$40M","rank":297},{"m":"Pottsville, PA","total_assets":15,"total_amount":40040280,"total_fmt":"$40M","rank":298},{"m":"Russellville, AL","total_assets":2,"total_amount":39987607,"total_fmt":"$40M","rank":299},{"m":"Stillwater, OK","total_assets":11,"total_amount":39836830,"total_fmt":"$40M","rank":300},{"m":"Wilson, NC","total_assets":7,"total_amount":39498696,"total_fmt":"$39M","rank":301},{"m":"Brookings, SD","total_assets":3,"total_amount":39391425,"total_fmt":"$39M","rank":302},{"m":"Bismarck, ND","total_assets":24,"total_amount":38814417,"total_fmt":"$39M","rank":303},{"m":"Kiryas Joel-Poughkeepsie-Newburgh, NY","total_assets":74,"total_amount":38810619,"total_fmt":"$39M","rank":304},{"m":"Athens, TN","total_assets":6,"total_amount":38248396,"total_fmt":"$38M","rank":305},{"m":"Jackson, MI","total_assets":20,"total_amount":37585048,"total_fmt":"$38M","rank":306},{"m":"Santa Rosa-Petaluma, CA","total_assets":62,"total_amount":37222206,"total_fmt":"$37M","rank":307},{"m":"Dover, DE","total_assets":57,"total_amount":36598568,"total_fmt":"$37M","rank":308},{"m":"Auburn, NY","total_assets":12,"total_amount":36288351,"total_fmt":"$36M","rank":309},{"m":"Modesto, CA","total_assets":29,"total_amount":35968675,"total_fmt":"$36M","rank":310},{"m":"Fayetteville, TN","total_assets":3,"total_amount":35953329,"total_fmt":"$36M","rank":311},{"m":"Decatur, AL","total_assets":30,"total_amount":35416150,"total_fmt":"$35M","rank":312},{"m":"Watertown-Fort Drum, NY","total_assets":40,"total_amount":35409453,"total_fmt":"$35M","rank":313},{"m":"Danville, IL","total_assets":6,"total_amount":34993199,"total_fmt":"$35M","rank":314},{"m":"Gettysburg, PA","total_assets":19,"total_amount":34852178,"total_fmt":"$35M","rank":315},{"m":"Hilo-Kailua, HI","total_assets":24,"total_amount":34175349,"total_fmt":"$34M","rank":316},{"m":"Muscatine, IA","total_assets":9,"total_amount":34031757,"total_fmt":"$34M","rank":317},{"m":"Kapaa, HI","total_assets":12,"total_amount":33783094,"total_fmt":"$34M","rank":318},{"m":"Green Bay, WI","total_assets":46,"total_amount":33411281,"total_fmt":"$33M","rank":319},{"m":"Vidalia, GA","total_assets":2,"total_amount":32203802,"total_fmt":"$32M","rank":320},{"m":"Hagerstown-Martinsburg, MD-WV","total_assets":46,"total_amount":32106249,"total_fmt":"$32M","rank":321},{"m":"Meadville, PA","total_assets":14,"total_amount":31797355,"total_fmt":"$32M","rank":322},{"m":"Coos Bay-North Bend, OR","total_assets":8,"total_amount":31531599,"total_fmt":"$32M","rank":323},{"m":"Lumberton, NC","total_assets":18,"total_amount":30856612,"total_fmt":"$31M","rank":324},{"m":"Marquette, MI","total_assets":5,"total_amount":30764839,"total_fmt":"$31M","rank":325},{"m":"Espanola, NM","total_assets":9,"total_amount":30515917,"total_fmt":"$31M","rank":326},{"m":"Chattanooga, TN-GA","total_assets":51,"total_amount":30387355,"total_fmt":"$30M","rank":327},{"m":"Jasper, IN","total_assets":13,"total_amount":30318281,"total_fmt":"$30M","rank":328},{"m":"Hermiston-Pendleton, OR","total_assets":16,"total_amount":29885656,"total_fmt":"$30M","rank":329},{"m":"Ocean Pines, MD","total_assets":10,"total_amount":29768185,"total_fmt":"$30M","rank":330},{"m":"Kalispell, MT","total_assets":20,"total_amount":29661352,"total_fmt":"$30M","rank":331},{"m":"Henderson, KY","total_assets":11,"total_amount":29601250,"total_fmt":"$30M","rank":332},{"m":"Fresno, CA","total_assets":76,"total_amount":29292723,"total_fmt":"$29M","rank":333},{"m":"Gainesville, GA","total_assets":24,"total_amount":29163956,"total_fmt":"$29M","rank":334},{"m":"Dubuque, IA","total_assets":10,"total_amount":28463197,"total_fmt":"$28M","rank":335},{"m":"Beaver Dam, WI","total_assets":9,"total_amount":27907600,"total_fmt":"$28M","rank":336},{"m":"Magnolia, AR","total_assets":3,"total_amount":27799628,"total_fmt":"$28M","rank":337},{"m":"Mount Sterling, KY","total_assets":3,"total_amount":27775182,"total_fmt":"$28M","rank":338},{"m":"Dothan, AL","total_assets":31,"total_amount":27433469,"total_fmt":"$27M","rank":339},{"m":"Olympia-Lacey-Tumwater, WA","total_assets":51,"total_amount":27307829,"total_fmt":"$27M","rank":340},{"m":"Grand Junction, CO","total_assets":13,"total_amount":27210775,"total_fmt":"$27M","rank":341},{"m":"Sheboygan, WI","total_assets":5,"total_amount":27019282,"total_fmt":"$27M","rank":342},{"m":"Vicksburg, MS","total_assets":39,"total_amount":26889021,"total_fmt":"$27M","rank":343},{"m":"Greeneville, TN","total_assets":7,"total_amount":26501197,"total_fmt":"$27M","rank":344},{"m":"Bend, OR","total_assets":46,"total_amount":26405902,"total_fmt":"$26M","rank":345},{"m":"Natchitoches, LA","total_assets":7,"total_amount":26380697,"total_fmt":"$26M","rank":346},{"m":"Miami, OK","total_assets":6,"total_amount":26141894,"total_fmt":"$26M","rank":347},{"m":"Fort Smith, AR-OK","total_assets":39,"total_amount":25812285,"total_fmt":"$26M","rank":348},{"m":"Olean, NY","total_assets":12,"total_amount":25558638,"total_fmt":"$26M","rank":349},{"m":"Concord, NH","total_assets":39,"total_amount":25348711,"total_fmt":"$25M","rank":350},{"m":"Norfolk, NE","total_assets":7,"total_amount":24887757,"total_fmt":"$25M","rank":351},{"m":"Yuba City, CA","total_assets":22,"total_amount":24435401,"total_fmt":"$24M","rank":352},{"m":"Salem, OH","total_assets":11,"total_amount":24425900,"total_fmt":"$24M","rank":353},{"m":"Hattiesburg, MS","total_assets":23,"total_amount":24147484,"total_fmt":"$24M","rank":354},{"m":"Sherman-Denison, TX","total_assets":18,"total_amount":23330516,"total_fmt":"$23M","rank":355},{"m":"Atlantic City-Hammonton, NJ","total_assets":32,"total_amount":23324425,"total_fmt":"$23M","rank":356},{"m":"Columbia, MO","total_assets":25,"total_amount":23092302,"total_fmt":"$23M","rank":357},{"m":"Durant, OK","total_assets":8,"total_amount":23071998,"total_fmt":"$23M","rank":358},{"m":"Springfield, OH","total_assets":24,"total_amount":23057603,"total_fmt":"$23M","rank":359},{"m":"Florence-Muscle Shoals, AL","total_assets":11,"total_amount":22910488,"total_fmt":"$23M","rank":360},{"m":"Poplar Bluff, MO","total_assets":9,"total_amount":22754245,"total_fmt":"$23M","rank":361},{"m":"Elizabeth City, NC","total_assets":10,"total_amount":22276504,"total_fmt":"$22M","rank":362},{"m":"Greenwood, SC","total_assets":5,"total_amount":22058000,"total_fmt":"$22M","rank":363},{"m":"Warsaw, IN","total_assets":8,"total_amount":21848874,"total_fmt":"$22M","rank":364},{"m":"Hood River, OR","total_assets":14,"total_amount":21721161,"total_fmt":"$22M","rank":365},{"m":"East Stroudsburg, PA","total_assets":26,"total_amount":21656430,"total_fmt":"$22M","rank":366},{"m":"Bellingham, WA","total_assets":44,"total_amount":21295456,"total_fmt":"$21M","rank":367},{"m":"Billings, MT","total_assets":32,"total_amount":20993203,"total_fmt":"$21M","rank":368},{"m":"Winona, MN","total_assets":10,"total_amount":20914465,"total_fmt":"$21M","rank":369},{"m":"Duluth, MN-WI","total_assets":35,"total_amount":20791126,"total_fmt":"$21M","rank":370},{"m":"Camden, AR","total_assets":7,"total_amount":20768692,"total_fmt":"$21M","rank":371},{"m":"Saginaw, MI","total_assets":22,"total_amount":20522675,"total_fmt":"$21M","rank":372},{"m":"Barre, VT","total_assets":19,"total_amount":20510174,"total_fmt":"$21M","rank":373},{"m":"Eau Claire, WI","total_assets":28,"total_amount":19931992,"total_fmt":"$20M","rank":374},{"m":"Easton, MD","total_assets":13,"total_amount":19860858,"total_fmt":"$20M","rank":375},{"m":"Sebastian-Vero Beach-West Vero Corridor, FL","total_assets":23,"total_amount":19555048,"total_fmt":"$20M","rank":376},{"m":"Starkville, MS","total_assets":8,"total_amount":19119756,"total_fmt":"$19M","rank":377},{"m":"Warren, PA","total_assets":7,"total_amount":19046597,"total_fmt":"$19M","rank":378},{"m":"McAlester, OK","total_assets":21,"total_amount":18978292,"total_fmt":"$19M","rank":379},{"m":"Paducah, KY-IL","total_assets":17,"total_amount":18690965,"total_fmt":"$19M","rank":380},{"m":"Danville, VA","total_assets":6,"total_amount":18646283,"total_fmt":"$19M","rank":381},{"m":"Keene, NH","total_assets":19,"total_amount":18569831,"total_fmt":"$19M","rank":382},{"m":"Lawrence, KS","total_assets":18,"total_amount":18241945,"total_fmt":"$18M","rank":383},{"m":"Key West-Key Largo, FL","total_assets":33,"total_amount":18206997,"total_fmt":"$18M","rank":384},{"m":"Somerset, PA","total_assets":17,"total_amount":18071309,"total_fmt":"$18M","rank":385},{"m":"Mount Vernon, IL","total_assets":5,"total_amount":17590839,"total_fmt":"$18M","rank":386},{"m":"Sault Ste. Marie, MI","total_assets":8,"total_amount":17560047,"total_fmt":"$18M","rank":387},{"m":"Myrtle Beach-Conway-North Myrtle Beach, SC","total_assets":23,"total_amount":17380473,"total_fmt":"$17M","rank":388},{"m":"Hailey, ID","total_assets":3,"total_amount":17340514,"total_fmt":"$17M","rank":389},{"m":"Blackfoot, ID","total_assets":5,"total_amount":17295365,"total_fmt":"$17M","rank":390},{"m":"Rochester, MN","total_assets":15,"total_amount":17231574,"total_fmt":"$17M","rank":391},{"m":"Hickory-Lenoir-Morganton, NC","total_assets":35,"total_amount":17203120,"total_fmt":"$17M","rank":392},{"m":"Opelousas, LA","total_assets":6,"total_amount":16882256,"total_fmt":"$17M","rank":393},{"m":"Crescent City, CA","total_assets":2,"total_amount":16703840,"total_fmt":"$17M","rank":394},{"m":"Iowa City, IA","total_assets":18,"total_amount":16694920,"total_fmt":"$17M","rank":395},{"m":"Iron Mountain, MI-WI","total_assets":2,"total_amount":16359348,"total_fmt":"$16M","rank":396},{"m":"Missoula, MT","total_assets":30,"total_amount":16350234,"total_fmt":"$16M","rank":397},{"m":"Hot Springs, AR","total_assets":20,"total_amount":16204576,"total_fmt":"$16M","rank":398},{"m":"Cedar City, UT","total_assets":9,"total_amount":16119395,"total_fmt":"$16M","rank":399},{"m":"El Centro, CA","total_assets":17,"total_amount":16073270,"total_fmt":"$16M","rank":400},{"m":"Lubbock, TX","total_assets":16,"total_amount":16018586,"total_fmt":"$16M","rank":401},{"m":"Corvallis, OR","total_assets":13,"total_amount":15999079,"total_fmt":"$16M","rank":402},{"m":"Goldsboro, NC","total_assets":39,"total_amount":15882748,"total_fmt":"$16M","rank":403},{"m":"Alamogordo, NM","total_assets":28,"total_amount":15880407,"total_fmt":"$16M","rank":404},{"m":"Yakima, WA","total_assets":21,"total_amount":15730385,"total_fmt":"$16M","rank":405},{"m":"Racine-Mount Pleasant, WI","total_assets":22,"total_amount":15692030,"total_fmt":"$16M","rank":406},{"m":"Urbana, OH","total_assets":4,"total_amount":15325599,"total_fmt":"$15M","rank":407},{"m":"Tuscaloosa, AL","total_assets":24,"total_amount":15272202,"total_fmt":"$15M","rank":408},{"m":"Ames, IA","total_assets":16,"total_amount":15086061,"total_fmt":"$15M","rank":409},{"m":"Eureka-Arcata, CA","total_assets":7,"total_amount":15030890,"total_fmt":"$15M","rank":410},{"m":"Big Rapids, MI","total_assets":3,"total_amount":14809379,"total_fmt":"$15M","rank":411},{"m":"Rutland, VT","total_assets":9,"total_amount":14801752,"total_fmt":"$15M","rank":412},{"m":"Dublin, GA","total_assets":7,"total_amount":14772715,"total_fmt":"$15M","rank":413},{"m":"Blytheville, AR","total_assets":4,"total_amount":14735546,"total_fmt":"$15M","rank":414},{"m":"Salisbury, MD","total_assets":24,"total_amount":14461872,"total_fmt":"$14M","rank":415},{"m":"Port Angeles, WA","total_assets":8,"total_amount":13715957,"total_fmt":"$14M","rank":416},{"m":"Medford, OR","total_assets":28,"total_amount":13649651,"total_fmt":"$14M","rank":417},{"m":"Winchester, VA-WV","total_assets":22,"total_amount":13484108,"total_fmt":"$13M","rank":418},{"m":"Kingsland, GA","total_assets":16,"total_amount":13441929,"total_fmt":"$13M","rank":419},{"m":"Elmira, NY","total_assets":9,"total_amount":13144781,"total_fmt":"$13M","rank":420},{"m":"Mankato, MN","total_assets":18,"total_amount":13114958,"total_fmt":"$13M","rank":421},{"m":"Shelby-Kings Mountain, NC","total_assets":11,"total_amount":13092873,"total_fmt":"$13M","rank":422},{"m":"Murray, KY","total_assets":5,"total_amount":12845808,"total_fmt":"$13M","rank":423},{"m":"Greenfield, MA","total_assets":22,"total_amount":12522391,"total_fmt":"$13M","rank":424},{"m":"Wenatchee-East Wenatchee, WA","total_assets":23,"total_amount":12350520,"total_fmt":"$12M","rank":425},{"m":"Alexander City, AL","total_assets":7,"total_amount":12192610,"total_fmt":"$12M","rank":426},{"m":"Merced, CA","total_assets":4,"total_amount":12013513,"total_fmt":"$12M","rank":427},{"m":"Glens Falls, NY","total_assets":11,"total_amount":11908793,"total_fmt":"$12M","rank":428},{"m":"Butte-Silver Bow, MT","total_assets":10,"total_amount":11708838,"total_fmt":"$12M","rank":429},{"m":"Ponca City, OK","total_assets":10,"total_amount":11625533,"total_fmt":"$12M","rank":430},{"m":"Athens, OH","total_assets":8,"total_amount":11619767,"total_fmt":"$12M","rank":431},{"m":"Kinston, NC","total_assets":9,"total_amount":11579769,"total_fmt":"$12M","rank":432},{"m":"Waterloo-Cedar Falls, IA","total_assets":17,"total_amount":11565200,"total_fmt":"$12M","rank":433},{"m":"Cleveland, TN","total_assets":5,"total_amount":11364808,"total_fmt":"$11M","rank":434},{"m":"Tyler, TX","total_assets":15,"total_amount":11299674,"total_fmt":"$11M","rank":435},{"m":"LaGrange, GA-AL","total_assets":19,"total_amount":11243112,"total_fmt":"$11M","rank":436},{"m":"Monroe, LA","total_assets":17,"total_amount":11169485,"total_fmt":"$11M","rank":437},{"m":"Winchester, TN","total_assets":8,"total_amount":11136672,"total_fmt":"$11M","rank":438},{"m":"Breckenridge, CO","total_assets":6,"total_amount":10806850,"total_fmt":"$11M","rank":439},{"m":"Jackson, WY-ID","total_assets":14,"total_amount":10618680,"total_fmt":"$11M","rank":440},{"m":"Lebanon, MO","total_assets":5,"total_amount":10523072,"total_fmt":"$11M","rank":441},{"m":"Picayune, MS","total_assets":9,"total_amount":10350274,"total_fmt":"$10M","rank":442},{"m":"Johnson City, TN","total_assets":8,"total_amount":10293256,"total_fmt":"$10M","rank":443},{"m":"Baraboo, WI","total_assets":12,"total_amount":10278766,"total_fmt":"$10M","rank":444},{"m":"Alexandria, LA","total_assets":21,"total_amount":10262844,"total_fmt":"$10M","rank":445},{"m":"Minden, LA","total_assets":4,"total_amount":10109475,"total_fmt":"$10M","rank":446},{"m":"Gadsden, AL","total_assets":7,"total_amount":10098032,"total_fmt":"$10M","rank":447},{"m":"Brainerd, MN","total_assets":14,"total_amount":9900460,"total_fmt":"$10M","rank":448},{"m":"Bucyrus, OH","total_assets":5,"total_amount":9788029,"total_fmt":"$10M","rank":449},{"m":"Brevard, NC","total_assets":5,"total_amount":9646768,"total_fmt":"$10M","rank":450},{"m":"Punta Gorda, FL","total_assets":13,"total_amount":9427806,"total_fmt":"$9M","rank":451},{"m":"Seaford, DE","total_assets":24,"total_amount":9423126,"total_fmt":"$9M","rank":452},{"m":"Jackson, TN","total_assets":15,"total_amount":9254751,"total_fmt":"$9M","rank":453},{"m":"Shawnee, OK","total_assets":11,"total_amount":9202924,"total_fmt":"$9M","rank":454},{"m":"Clarksdale, MS","total_assets":2,"total_amount":9116934,"total_fmt":"$9M","rank":455},{"m":"Wooster, OH","total_assets":11,"total_amount":9028071,"total_fmt":"$9M","rank":456},{"m":"Meridian, MS","total_assets":30,"total_amount":9021756,"total_fmt":"$9M","rank":457},{"m":"Terre Haute, IN","total_assets":22,"total_amount":8920429,"total_fmt":"$9M","rank":458},{"m":"Rolla, MO","total_assets":12,"total_amount":8855484,"total_fmt":"$9M","rank":459},{"m":"Niles, MI","total_assets":16,"total_amount":8843368,"total_fmt":"$9M","rank":460},{"m":"Wapakoneta, OH","total_assets":2,"total_amount":8797771,"total_fmt":"$9M","rank":461},{"m":"Rocky Mount, NC","total_assets":12,"total_amount":8733697,"total_fmt":"$9M","rank":462},{"m":"Hermitage, PA","total_assets":15,"total_amount":8692992,"total_fmt":"$9M","rank":463},{"m":"Massena-Ogdensburg, NY","total_assets":13,"total_amount":8447249,"total_fmt":"$8M","rank":464},{"m":"Pullman, WA","total_assets":9,"total_amount":8313748,"total_fmt":"$8M","rank":465},{"m":"Flint, MI","total_assets":21,"total_amount":8250084,"total_fmt":"$8M","rank":466},{"m":"Ardmore, OK","total_assets":4,"total_amount":8241442,"total_fmt":"$8M","rank":467},{"m":"Longview, TX","total_assets":22,"total_amount":8240736,"total_fmt":"$8M","rank":468},{"m":"Faribault-Northfield, MN","total_assets":8,"total_amount":8178344,"total_fmt":"$8M","rank":469},{"m":"Carlsbad-Artesia, NM","total_assets":3,"total_amount":8114328,"total_fmt":"$8M","rank":470},{"m":"Richmond, IN","total_assets":4,"total_amount":8084791,"total_fmt":"$8M","rank":471},{"m":"Jamestown, ND","total_assets":2,"total_amount":8049617,"total_fmt":"$8M","rank":472},{"m":"Pocatello, ID","total_assets":11,"total_amount":8009811,"total_fmt":"$8M","rank":473},{"m":"Kearney, NE","total_assets":6,"total_amount":7988159,"total_fmt":"$8M","rank":474},{"m":"Salina, KS","total_assets":16,"total_amount":7951258,"total_fmt":"$8M","rank":475},{"m":"Plattsburgh, NY","total_assets":7,"total_amount":7937457,"total_fmt":"$8M","rank":476},{"m":"Wausau, WI","total_assets":11,"total_amount":7774493,"total_fmt":"$8M","rank":477},{"m":"Wheeling, WV-OH","total_assets":8,"total_amount":7774233,"total_fmt":"$8M","rank":478},{"m":"Ruston, LA","total_assets":5,"total_amount":7670779,"total_fmt":"$8M","rank":479},{"m":"Sheridan, WY","total_assets":18,"total_amount":7626433,"total_fmt":"$8M","rank":480},{"m":"Abilene, TX","total_assets":29,"total_amount":7614223,"total_fmt":"$8M","rank":481},{"m":"Moses Lake, WA","total_assets":8,"total_amount":7590315,"total_fmt":"$8M","rank":482},{"m":"Tupelo, MS","total_assets":11,"total_amount":7501167,"total_fmt":"$8M","rank":483},{"m":"Albemarle, NC","total_assets":16,"total_amount":7475386,"total_fmt":"$7M","rank":484},{"m":"Flagstaff, AZ","total_assets":13,"total_amount":7376672,"total_fmt":"$7M","rank":485},{"m":"Clinton, IA","total_assets":3,"total_amount":7331056,"total_fmt":"$7M","rank":486},{"m":"Spearfish, SD","total_assets":4,"total_amount":7301314,"total_fmt":"$7M","rank":487},{"m":"Oneonta, NY","total_assets":5,"total_amount":7217742,"total_fmt":"$7M","rank":488},{"m":"Watertown-Fort Atkinson, WI","total_assets":9,"total_amount":7132192,"total_fmt":"$7M","rank":489},{"m":"Bradford, PA","total_assets":3,"total_amount":7125361,"total_fmt":"$7M","rank":490},{"m":"Bartlesville, OK","total_assets":5,"total_amount":7108102,"total_fmt":"$7M","rank":491},{"m":"Sanford, NC","total_assets":10,"total_amount":7076944,"total_fmt":"$7M","rank":492},{"m":"Durango, CO","total_assets":8,"total_amount":7055353,"total_fmt":"$7M","rank":493},{"m":"Albany, OR","total_assets":16,"total_amount":7003367,"total_fmt":"$7M","rank":494},{"m":"Celina, OH","total_assets":4,"total_amount":6999303,"total_fmt":"$7M","rank":495},{"m":"Fremont, OH","total_assets":2,"total_amount":6913718,"total_fmt":"$7M","rank":496},{"m":"Sevierville, TN","total_assets":3,"total_amount":6864217,"total_fmt":"$7M","rank":497},{"m":"Sandpoint, ID","total_assets":14,"total_amount":6847613,"total_fmt":"$7M","rank":498},{"m":"Plymouth, IN","total_assets":3,"total_amount":6783699,"total_fmt":"$7M","rank":499},{"m":"Kingston, NY","total_assets":19,"total_amount":6716386,"total_fmt":"$7M","rank":500},{"m":"Carroll, IA","total_assets":5,"total_amount":6707020,"total_fmt":"$7M","rank":501},{"m":"Zanesville, OH","total_assets":5,"total_amount":6681255,"total_fmt":"$7M","rank":502},{"m":"Gardnerville Ranchos, NV-CA","total_assets":16,"total_amount":6582984,"total_fmt":"$7M","rank":503},{"m":"Washington, IN","total_assets":11,"total_amount":6529651,"total_fmt":"$7M","rank":504},{"m":"Milledgeville, GA","total_assets":6,"total_amount":6453296,"total_fmt":"$6M","rank":505},{"m":"Lewisburg, PA","total_assets":7,"total_amount":6393998,"total_fmt":"$6M","rank":506},{"m":"Laurinburg, NC","total_assets":8,"total_amount":6232096,"total_fmt":"$6M","rank":507},{"m":"Bainbridge, GA","total_assets":4,"total_amount":6228561,"total_fmt":"$6M","rank":508},{"m":"Cookeville, TN","total_assets":17,"total_amount":6180492,"total_fmt":"$6M","rank":509},{"m":"Pahrump, NV","total_assets":8,"total_amount":6162189,"total_fmt":"$6M","rank":510},{"m":"Le Mars, IA","total_assets":4,"total_amount":6132833,"total_fmt":"$6M","rank":511},{"m":"Ozark, AL","total_assets":18,"total_amount":6111552,"total_fmt":"$6M","rank":512},{"m":"Hanford-Corcoran, CA","total_assets":10,"total_amount":6054718,"total_fmt":"$6M","rank":513},{"m":"Troy, AL","total_assets":7,"total_amount":5780592,"total_fmt":"$6M","rank":514},{"m":"Fairmont, WV","total_assets":9,"total_amount":5768225,"total_fmt":"$6M","rank":515},{"m":"Parkersburg-Vienna, WV","total_assets":9,"total_amount":5767228,"total_fmt":"$6M","rank":516},{"m":"Marion, IN","total_assets":3,"total_amount":5753626,"total_fmt":"$6M","rank":517},{"m":"Los Alamos, NM","total_assets":4,"total_amount":5715476,"total_fmt":"$6M","rank":518},{"m":"Albertville, AL","total_assets":13,"total_amount":5701747,"total_fmt":"$6M","rank":519},{"m":"Redding, CA","total_assets":13,"total_amount":5659318,"total_fmt":"$6M","rank":520},{"m":"Wahpeton, ND-MN","total_assets":3,"total_amount":5614743,"total_fmt":"$6M","rank":521},{"m":"Sandusky, OH","total_assets":16,"total_amount":5611219,"total_fmt":"$6M","rank":522},{"m":"Sparta, WI","total_assets":8,"total_amount":5562405,"total_fmt":"$6M","rank":523},{"m":"Hillsdale, MI","total_assets":3,"total_amount":5486639,"total_fmt":"$5M","rank":524},{"m":"Bedford, IN","total_assets":17,"total_amount":5460961,"total_fmt":"$5M","rank":525},{"m":"Traverse City, MI","total_assets":27,"total_amount":5456273,"total_fmt":"$5M","rank":526},{"m":"Fredericksburg, TX","total_assets":5,"total_amount":5433828,"total_fmt":"$5M","rank":527},{"m":"Carbondale, IL","total_assets":6,"total_amount":5282573,"total_fmt":"$5M","rank":528},{"m":"Fond du Lac, WI","total_assets":8,"total_amount":5248248,"total_fmt":"$5M","rank":529},{"m":"Altoona, PA","total_assets":16,"total_amount":5238389,"total_fmt":"$5M","rank":530},{"m":"Susanville, CA","total_assets":8,"total_amount":5211781,"total_fmt":"$5M","rank":531},{"m":"Batavia, NY","total_assets":2,"total_amount":5186234,"total_fmt":"$5M","rank":532},{"m":"Wildwood-The Villages, FL","total_assets":7,"total_amount":5160779,"total_fmt":"$5M","rank":533},{"m":"Palatka, FL","total_assets":3,"total_amount":5087002,"total_fmt":"$5M","rank":534},{"m":"Red Bluff, CA","total_assets":3,"total_amount":5084627,"total_fmt":"$5M","rank":535},{"m":"Lock Haven, PA","total_assets":8,"total_amount":5082364,"total_fmt":"$5M","rank":536},{"m":"Cambridge, MD","total_assets":9,"total_amount":5053868,"total_fmt":"$5M","rank":537},{"m":"Putnam, CT","total_assets":13,"total_amount":4929609,"total_fmt":"$5M","rank":538},{"m":"Bonham, TX","total_assets":5,"total_amount":4922777,"total_fmt":"$5M","rank":539},{"m":"Natchez, MS-LA","total_assets":6,"total_amount":4913995,"total_fmt":"$5M","rank":540},{"m":"Oil City, PA","total_assets":6,"total_amount":4878657,"total_fmt":"$5M","rank":541},{"m":"Laramie, WY","total_assets":11,"total_amount":4845929,"total_fmt":"$5M","rank":542},{"m":"Prescott Valley-Prescott, AZ","total_assets":22,"total_amount":4744597,"total_fmt":"$5M","rank":543},{"m":"Bemidji, MN","total_assets":9,"total_amount":4635425,"total_fmt":"$5M","rank":544},{"m":"Duncan, OK","total_assets":14,"total_amount":4608931,"total_fmt":"$5M","rank":545},{"m":"Arkansas City-Winfield, KS","total_assets":3,"total_amount":4601251,"total_fmt":"$5M","rank":546},{"m":"Grenada, MS","total_assets":7,"total_amount":4596280,"total_fmt":"$5M","rank":547},{"m":"Alma, MI","total_assets":3,"total_amount":4537434,"total_fmt":"$5M","rank":548},{"m":"Mansfield, OH","total_assets":16,"total_amount":4537403,"total_fmt":"$5M","rank":549},{"m":"Brenham, TX","total_assets":5,"total_amount":4475469,"total_fmt":"$4M","rank":550},{"m":"Bennington, VT","total_assets":6,"total_amount":4463410,"total_fmt":"$4M","rank":551},{"m":"Enid, OK","total_assets":16,"total_amount":4438539,"total_fmt":"$4M","rank":552},{"m":"Torrington, CT","total_assets":10,"total_amount":4381359,"total_fmt":"$4M","rank":553},{"m":"Staunton-Stuarts Draft, VA","total_assets":7,"total_amount":4343393,"total_fmt":"$4M","rank":554},{"m":"Klamath Falls, OR","total_assets":11,"total_amount":4321398,"total_fmt":"$4M","rank":555},{"m":"Brownsville-Harlingen, TX","total_assets":18,"total_amount":4242538,"total_fmt":"$4M","rank":556},{"m":"Michigan City-La Porte, IN","total_assets":8,"total_amount":4183292,"total_fmt":"$4M","rank":557},{"m":"Aguadilla, PR","total_assets":9,"total_amount":4182924,"total_fmt":"$4M","rank":558},{"m":"Monroe, MI","total_assets":7,"total_amount":4169134,"total_fmt":"$4M","rank":559},{"m":"Lufkin, TX","total_assets":7,"total_amount":4137629,"total_fmt":"$4M","rank":560},{"m":"Clovis, NM","total_assets":23,"total_amount":4032055,"total_fmt":"$4M","rank":561},{"m":"Riverton, WY","total_assets":3,"total_amount":3918122,"total_fmt":"$4M","rank":562},{"m":"Truckee-Grass Valley, CA","total_assets":21,"total_amount":3891296,"total_fmt":"$4M","rank":563},{"m":"Grants Pass, OR","total_assets":9,"total_amount":3860264,"total_fmt":"$4M","rank":564},{"m":"Paris, TX","total_assets":12,"total_amount":3845420,"total_fmt":"$4M","rank":565},{"m":"Marshalltown, IA","total_assets":3,"total_amount":3830453,"total_fmt":"$4M","rank":566},{"m":"Freeport, IL","total_assets":3,"total_amount":3786403,"total_fmt":"$4M","rank":567},{"m":"Evanston, WY-UT","total_assets":3,"total_amount":3748499,"total_fmt":"$4M","rank":568},{"m":"Lewiston-Auburn, ME","total_assets":19,"total_amount":3547848,"total_fmt":"$4M","rank":569},{"m":"Odessa, TX","total_assets":5,"total_amount":3467498,"total_fmt":"$3M","rank":570},{"m":"Monticello, NY","total_assets":6,"total_amount":3369110,"total_fmt":"$3M","rank":571},{"m":"Florence, SC","total_assets":14,"total_amount":3357803,"total_fmt":"$3M","rank":572},{"m":"DuBois, PA","total_assets":8,"total_amount":3325733,"total_fmt":"$3M","rank":573},{"m":"Mount Airy, NC","total_assets":5,"total_amount":3234074,"total_fmt":"$3M","rank":574},{"m":"Waynesville, NC","total_assets":3,"total_amount":3187734,"total_fmt":"$3M","rank":575},{"m":"Battle Creek, MI","total_assets":16,"total_amount":3163941,"total_fmt":"$3M","rank":576},{"m":"Ellensburg, WA","total_assets":6,"total_amount":3137534,"total_fmt":"$3M","rank":577},{"m":"Vincennes, IN","total_assets":3,"total_amount":2983836,"total_fmt":"$3M","rank":578},{"m":"Sumter, SC","total_assets":8,"total_amount":2890556,"total_fmt":"$3M","rank":579},{"m":"Amsterdam, NY","total_assets":4,"total_amount":2826574,"total_fmt":"$3M","rank":580},{"m":"Albany, GA","total_assets":23,"total_amount":2782688,"total_fmt":"$3M","rank":581},{"m":"Muskogee, OK","total_assets":13,"total_amount":2723889,"total_fmt":"$3M","rank":582},{"m":"Thomasville, GA","total_assets":9,"total_amount":2710890,"total_fmt":"$3M","rank":583},{"m":"Gaffney, SC","total_assets":4,"total_amount":2654376,"total_fmt":"$3M","rank":584},{"m":"Murrells Inlet, SC","total_assets":7,"total_amount":2646626,"total_fmt":"$3M","rank":585},{"m":"Roseburg, OR","total_assets":7,"total_amount":2635346,"total_fmt":"$3M","rank":586},{"m":"Nogales, AZ","total_assets":7,"total_amount":2625534,"total_fmt":"$3M","rank":587},{"m":"Russellville, AR","total_assets":18,"total_amount":2619818,"total_fmt":"$3M","rank":588},{"m":"Cortland, NY","total_assets":6,"total_amount":2595754,"total_fmt":"$3M","rank":589},{"m":"New Philadelphia-Dover, OH","total_assets":9,"total_amount":2578582,"total_fmt":"$3M","rank":590},{"m":"Sulphur Springs, TX","total_assets":4,"total_amount":2565048,"total_fmt":"$3M","rank":591},{"m":"Ukiah, CA","total_assets":10,"total_amount":2562222,"total_fmt":"$3M","rank":592},{"m":"Holland, MI","total_assets":9,"total_amount":2560063,"total_fmt":"$3M","rank":593},{"m":"Edwards, CO","total_assets":4,"total_amount":2490451,"total_fmt":"$2M","rank":594},{"m":"Lima, OH","total_assets":11,"total_amount":2465864,"total_fmt":"$2M","rank":595},{"m":"Sebring, FL","total_assets":9,"total_amount":2452827,"total_fmt":"$2M","rank":596},{"m":"Sunbury, PA","total_assets":7,"total_amount":2423803,"total_fmt":"$2M","rank":597},{"m":"Jacksonville, IL","total_assets":3,"total_amount":2401730,"total_fmt":"$2M","rank":598},{"m":"Morristown, TN","total_assets":5,"total_amount":2338004,"total_fmt":"$2M","rank":599},{"m":"Mount Pleasant, MI","total_assets":5,"total_amount":2326847,"total_fmt":"$2M","rank":600},{"m":"Beatrice, NE","total_assets":4,"total_amount":2318093,"total_fmt":"$2M","rank":601},{"m":"Bellefontaine, OH","total_assets":4,"total_amount":2311154,"total_fmt":"$2M","rank":602},{"m":"Sedalia, MO","total_assets":6,"total_amount":2302547,"total_fmt":"$2M","rank":603},{"m":"Mount Pleasant, TX","total_assets":5,"total_amount":2280349,"total_fmt":"$2M","rank":604},{"m":"Ponce, PR","total_assets":22,"total_amount":2278558,"total_fmt":"$2M","rank":605},{"m":"Del Rio, TX","total_assets":20,"total_amount":2251738,"total_fmt":"$2M","rank":606},{"m":"Madisonville, KY","total_assets":7,"total_amount":2244271,"total_fmt":"$2M","rank":607},{"m":"Kirksville, MO","total_assets":3,"total_amount":2214037,"total_fmt":"$2M","rank":608},{"m":"San Angelo, TX","total_assets":22,"total_amount":2199196,"total_fmt":"$2M","rank":609},{"m":"Lewiston, ID-WA","total_assets":14,"total_amount":2196222,"total_fmt":"$2M","rank":610},{"m":"Twin Falls, ID","total_assets":10,"total_amount":2191721,"total_fmt":"$2M","rank":611},{"m":"Fallon, NV","total_assets":17,"total_amount":2174685,"total_fmt":"$2M","rank":612},{"m":"Walla Walla, WA","total_assets":7,"total_amount":2166373,"total_fmt":"$2M","rank":613},{"m":"Alpena, MI","total_assets":4,"total_amount":2146492,"total_fmt":"$2M","rank":614},{"m":"Sonora, CA","total_assets":9,"total_amount":2135367,"total_fmt":"$2M","rank":615},{"m":"Lexington, NE","total_assets":2,"total_amount":2088413,"total_fmt":"$2M","rank":616},{"m":"Maryville, MO","total_assets":3,"total_amount":2082215,"total_fmt":"$2M","rank":617},{"m":"Seneca Falls, NY","total_assets":3,"total_amount":2057341,"total_fmt":"$2M","rank":618},{"m":"Sayre, PA","total_assets":4,"total_amount":2029687,"total_fmt":"$2M","rank":619},{"m":"Monticello, IN","total_assets":1,"total_amount":2011835,"total_fmt":"$2M","rank":620},{"m":"Ottawa, IL","total_assets":10,"total_amount":2009496,"total_fmt":"$2M","rank":621},{"m":"Bluefield, WV-VA","total_assets":4,"total_amount":1931783,"total_fmt":"$2M","rank":622},{"m":"Homosassa Springs, FL","total_assets":8,"total_amount":1912177,"total_fmt":"$2M","rank":623},{"m":"Newport, TN","total_assets":2,"total_amount":1887344,"total_fmt":"$2M","rank":624},{"m":"St. Cloud, MN","total_assets":14,"total_amount":1873073,"total_fmt":"$2M","rank":625},{"m":"Greenville, OH","total_assets":4,"total_amount":1856758,"total_fmt":"$2M","rank":626},{"m":"Kerrville, TX","total_assets":5,"total_amount":1848969,"total_fmt":"$2M","rank":627},{"m":"Mineral Wells, TX","total_assets":3,"total_amount":1800550,"total_fmt":"$2M","rank":628},{"m":"Hutchinson, MN","total_assets":4,"total_amount":1773504,"total_fmt":"$2M","rank":629},{"m":"Granbury, TX","total_assets":4,"total_amount":1759257,"total_fmt":"$2M","rank":630},{"m":"Adrian, MI","total_assets":2,"total_amount":1726566,"total_fmt":"$2M","rank":631},{"m":"Bogalusa, LA","total_assets":4,"total_amount":1712487,"total_fmt":"$2M","rank":632},{"m":"Selinsgrove, PA","total_assets":3,"total_amount":1712159,"total_fmt":"$2M","rank":633},{"m":"Farmington, MO","total_assets":5,"total_amount":1689311,"total_fmt":"$2M","rank":634},{"m":"Lake Havasu City-Kingman, AZ","total_assets":11,"total_amount":1681887,"total_fmt":"$2M","rank":635},{"m":"Mayfield, KY","total_assets":4,"total_amount":1661719,"total_fmt":"$2M","rank":636},{"m":"Mountain Home, ID","total_assets":14,"total_amount":1661602,"total_fmt":"$2M","rank":637},{"m":"Sterling, IL","total_assets":3,"total_amount":1655238,"total_fmt":"$2M","rank":638},{"m":"Elko, NV","total_assets":5,"total_amount":1648944,"total_fmt":"$2M","rank":639},{"m":"Laurel, MS","total_assets":5,"total_amount":1645100,"total_fmt":"$2M","rank":640},{"m":"Fort Madison, IA","total_assets":3,"total_amount":1623379,"total_fmt":"$2M","rank":641},{"m":"Bowling Green, KY","total_assets":16,"total_amount":1614903,"total_fmt":"$2M","rank":642},{"m":"Searcy, AR","total_assets":5,"total_amount":1611250,"total_fmt":"$2M","rank":643},{"m":"St. Joseph, MO-KS","total_assets":11,"total_amount":1608431,"total_fmt":"$2M","rank":644},{"m":"Fergus Falls, MN","total_assets":4,"total_amount":1605747,"total_fmt":"$2M","rank":645},{"m":"Roanoke Rapids, NC","total_assets":5,"total_amount":1597813,"total_fmt":"$2M","rank":646},{"m":"Whitewater-Elkhorn, WI","total_assets":10,"total_amount":1579170,"total_fmt":"$2M","rank":647},{"m":"Shawano, WI","total_assets":4,"total_amount":1549379,"total_fmt":"$2M","rank":648},{"m":"Seneca, SC","total_assets":3,"total_amount":1512121,"total_fmt":"$2M","rank":649},{"m":"Glasgow, KY","total_assets":6,"total_amount":1433569,"total_fmt":"$1M","rank":650},{"m":"Jesup, GA","total_assets":7,"total_amount":1423358,"total_fmt":"$1M","rank":651},{"m":"Sidney, OH","total_assets":7,"total_amount":1412947,"total_fmt":"$1M","rank":652},{"m":"Huntingdon, PA","total_assets":8,"total_amount":1385331,"total_fmt":"$1M","rank":653},{"m":"Casper, WY","total_assets":10,"total_amount":1368668,"total_fmt":"$1M","rank":654},{"m":"Dalton, GA","total_assets":3,"total_amount":1357186,"total_fmt":"$1M","rank":655},{"m":"Scottsbluff, NE","total_assets":2,"total_amount":1352814,"total_fmt":"$1M","rank":656},{"m":"Yankton, SD","total_assets":7,"total_amount":1341221,"total_fmt":"$1M","rank":657},{"m":"Hammond, LA","total_assets":11,"total_amount":1340680,"total_fmt":"$1M","rank":658},{"m":"Kennett, MO","total_assets":1,"total_amount":1334195,"total_fmt":"$1M","rank":659},{"m":"Hudson, NY","total_assets":7,"total_amount":1311808,"total_fmt":"$1M","rank":660},{"m":"Escanaba, MI","total_assets":6,"total_amount":1296751,"total_fmt":"$1M","rank":661},{"m":"Owatonna, MN","total_assets":4,"total_amount":1296492,"total_fmt":"$1M","rank":662},{"m":"Cape Girardeau, MO-IL","total_assets":7,"total_amount":1266239,"total_fmt":"$1M","rank":663},{"m":"Hinesville, GA","total_assets":7,"total_amount":1259149,"total_fmt":"$1M","rank":664},{"m":"Columbus, NE","total_assets":3,"total_amount":1235055,"total_fmt":"$1M","rank":665},{"m":"Grand Rapids, MN","total_assets":9,"total_amount":1229529,"total_fmt":"$1M","rank":666},{"m":"New Ulm, MN","total_assets":3,"total_amount":1218732,"total_fmt":"$1M","rank":667},{"m":"Quincy, IL-MO","total_assets":11,"total_amount":1214626,"total_fmt":"$1M","rank":668},{"m":"Moscow, ID","total_assets":9,"total_amount":1196549,"total_fmt":"$1M","rank":669},{"m":"Huntington, IN","total_assets":3,"total_amount":1156430,"total_fmt":"$1M","rank":670},{"m":"Scottsboro, AL","total_assets":7,"total_amount":1151366,"total_fmt":"$1M","rank":671},{"m":"Alexandria, MN","total_assets":5,"total_amount":1120611,"total_fmt":"$1M","rank":672},{"m":"Waycross, GA","total_assets":4,"total_amount":1109793,"total_fmt":"$1M","rank":673},{"m":"Ludington, MI","total_assets":1,"total_amount":1098367,"total_fmt":"$1M","rank":674},{"m":"Hemlock Farms, PA","total_assets":6,"total_amount":1064188,"total_fmt":"$1M","rank":675},{"m":"Red Wing, MN","total_assets":7,"total_amount":1063804,"total_fmt":"$1M","rank":676},{"m":"Albert Lea, MN","total_assets":5,"total_amount":1062556,"total_fmt":"$1M","rank":677},{"m":"Statesboro, GA","total_assets":9,"total_amount":1045031,"total_fmt":"$1M","rank":678},{"m":"Rifle, CO","total_assets":5,"total_amount":1043541,"total_fmt":"$1M","rank":679},{"m":"Bloomington, IL","total_assets":7,"total_amount":1037113,"total_fmt":"$1M","rank":680},{"m":"Owensboro, KY","total_assets":7,"total_amount":1027465,"total_fmt":"$1M","rank":681},{"m":"Calhoun, GA","total_assets":4,"total_amount":1017724,"total_fmt":"$1M","rank":682},{"m":"North Platte, NE","total_assets":5,"total_amount":993559,"total_fmt":"$994K","rank":683},{"m":"Boone, NC","total_assets":6,"total_amount":987102,"total_fmt":"$987K","rank":684},{"m":"Rexburg, ID","total_assets":1,"total_amount":971719,"total_fmt":"$972K","rank":685},{"m":"Moultrie, GA","total_assets":4,"total_amount":942163,"total_fmt":"$942K","rank":686},{"m":"Grand Island, NE","total_assets":6,"total_amount":918859,"total_fmt":"$919K","rank":687},{"m":"Hastings, NE","total_assets":3,"total_amount":913287,"total_fmt":"$913K","rank":688},{"m":"Weirton-Steubenville, WV-OH","total_assets":3,"total_amount":905581,"total_fmt":"$906K","rank":689},{"m":"Victoria, TX","total_assets":3,"total_amount":894168,"total_fmt":"$894K","rank":690},{"m":"Bay City, MI","total_assets":5,"total_amount":886659,"total_fmt":"$887K","rank":691},{"m":"Pierre, SD","total_assets":11,"total_amount":878283,"total_fmt":"$878K","rank":692},{"m":"Pikeville, KY","total_assets":8,"total_amount":874710,"total_fmt":"$875K","rank":693},{"m":"Ketchikan, AK","total_assets":3,"total_amount":873344,"total_fmt":"$873K","rank":694},{"m":"Moberly, MO","total_assets":2,"total_amount":845380,"total_fmt":"$845K","rank":695},{"m":"Centralia, WA","total_assets":10,"total_amount":838429,"total_fmt":"$838K","rank":696},{"m":"Jacksonville, TX","total_assets":3,"total_amount":835875,"total_fmt":"$836K","rank":697},{"m":"Montrose, CO","total_assets":4,"total_amount":831087,"total_fmt":"$831K","rank":698},{"m":"Madison, IN","total_assets":7,"total_amount":816579,"total_fmt":"$817K","rank":699},{"m":"Charleston-Mattoon, IL","total_assets":6,"total_amount":784639,"total_fmt":"$785K","rank":700},{"m":"Mountain Home, AR","total_assets":13,"total_amount":748926,"total_fmt":"$749K","rank":701},{"m":"Crossville, TN","total_assets":2,"total_amount":746756,"total_fmt":"$747K","rank":702},{"m":"Norwalk, OH","total_assets":8,"total_amount":736317,"total_fmt":"$736K","rank":703},{"m":"Aberdeen, WA","total_assets":5,"total_amount":700401,"total_fmt":"$700K","rank":704},{"m":"Marietta, OH","total_assets":7,"total_amount":687420,"total_fmt":"$687K","rank":705},{"m":"Somerset, KY","total_assets":11,"total_amount":684682,"total_fmt":"$685K","rank":706},{"m":"Midland, TX","total_assets":8,"total_amount":683652,"total_fmt":"$684K","rank":707},{"m":"Corning, NY","total_assets":5,"total_amount":658108,"total_fmt":"$658K","rank":708},{"m":"Tahlequah, OK","total_assets":8,"total_amount":655379,"total_fmt":"$655K","rank":709},{"m":"West Plains, MO","total_assets":7,"total_amount":650429,"total_fmt":"$650K","rank":710},{"m":"Alamosa, CO","total_assets":2,"total_amount":636731,"total_fmt":"$637K","rank":711},{"m":"Steamboat Springs, CO","total_assets":5,"total_amount":609052,"total_fmt":"$609K","rank":712},{"m":"Angola, IN","total_assets":3,"total_amount":591679,"total_fmt":"$592K","rank":713},{"m":"Hannibal, MO","total_assets":6,"total_amount":581633,"total_fmt":"$582K","rank":714},{"m":"DeRidder, LA","total_assets":2,"total_amount":548400,"total_fmt":"$548K","rank":715},{"m":"El Dorado, AR","total_assets":3,"total_amount":547258,"total_fmt":"$547K","rank":716},{"m":"Williston, ND","total_assets":4,"total_amount":538261,"total_fmt":"$538K","rank":717},{"m":"Branson, MO","total_assets":4,"total_amount":517814,"total_fmt":"$518K","rank":718},{"m":"Vermillion, SD","total_assets":2,"total_amount":498546,"total_fmt":"$499K","rank":719},{"m":"Peru, IN","total_assets":5,"total_amount":488426,"total_fmt":"$488K","rank":720},{"m":"Clearlake, CA","total_assets":3,"total_amount":487021,"total_fmt":"$487K","rank":721},{"m":"Kingsville, TX","total_assets":2,"total_amount":482406,"total_fmt":"$482K","rank":722},{"m":"Watertown, SD","total_assets":5,"total_amount":478115,"total_fmt":"$478K","rank":723},{"m":"Ottawa, KS","total_assets":5,"total_amount":472968,"total_fmt":"$473K","rank":724},{"m":"Orangeburg, SC","total_assets":5,"total_amount":466734,"total_fmt":"$467K","rank":725},{"m":"La Grande, OR","total_assets":2,"total_amount":466729,"total_fmt":"$467K","rank":726},{"m":"Laredo, TX","total_assets":8,"total_amount":463330,"total_fmt":"$463K","rank":727},{"m":"Kill Devil Hills, NC","total_assets":5,"total_amount":461208,"total_fmt":"$461K","rank":728},{"m":"Show Low, AZ","total_assets":3,"total_amount":453318,"total_fmt":"$453K","rank":729},{"m":"Coco, PR","total_assets":5,"total_amount":451637,"total_fmt":"$452K","rank":730},{"m":"Palestine, TX","total_assets":3,"total_amount":447728,"total_fmt":"$448K","rank":731},{"m":"Hutchinson, KS","total_assets":8,"total_amount":441079,"total_fmt":"$441K","rank":732},{"m":"Astoria, OR","total_assets":8,"total_amount":437995,"total_fmt":"$438K","rank":733},{"m":"Campbellsville, KY","total_assets":4,"total_amount":420771,"total_fmt":"$421K","rank":734},{"m":"Lawrenceburg, TN","total_assets":2,"total_amount":420025,"total_fmt":"$420K","rank":735},{"m":"Sikeston, MO","total_assets":6,"total_amount":415111,"total_fmt":"$415K","rank":736},{"m":"Athens, TX","total_assets":5,"total_amount":412621,"total_fmt":"$413K","rank":737},{"m":"Manitowoc, WI","total_assets":3,"total_amount":402755,"total_fmt":"$403K","rank":738},{"m":"Pella, IA","total_assets":6,"total_amount":399940,"total_fmt":"$400K","rank":739},{"m":"Midland, MI","total_assets":4,"total_amount":398614,"total_fmt":"$399K","rank":740},{"m":"Coshocton, OH","total_assets":2,"total_amount":392675,"total_fmt":"$393K","rank":741},{"m":"Forest City, NC","total_assets":4,"total_amount":386300,"total_fmt":"$386K","rank":742},{"m":"Port Townsend, WA","total_assets":10,"total_amount":378774,"total_fmt":"$379K","rank":743},{"m":"Stevens Point-Plover, WI","total_assets":4,"total_amount":375915,"total_fmt":"$376K","rank":744},{"m":"McMinnville, TN","total_assets":4,"total_amount":375015,"total_fmt":"$375K","rank":745},{"m":"Middlesborough, KY","total_assets":1,"total_amount":372422,"total_fmt":"$372K","rank":746},{"m":"Decatur, IL","total_assets":5,"total_amount":366112,"total_fmt":"$366K","rank":747},{"m":"Huntsville, TX","total_assets":3,"total_amount":358002,"total_fmt":"$358K","rank":748},{"m":"Lake of the Woods, VA","total_assets":7,"total_amount":357214,"total_fmt":"$357K","rank":749},{"m":"Wabash, IN","total_assets":4,"total_amount":345972,"total_fmt":"$346K","rank":750},{"m":"Dickinson, ND","total_assets":6,"total_amount":343671,"total_fmt":"$344K","rank":751},{"m":"Rome, GA","total_assets":3,"total_amount":337161,"total_fmt":"$337K","rank":752},{"m":"Canon City, CO","total_assets":6,"total_amount":335284,"total_fmt":"$335K","rank":753},{"m":"Alice, TX","total_assets":5,"total_amount":325706,"total_fmt":"$326K","rank":754},{"m":"Fremont, NE","total_assets":4,"total_amount":324519,"total_fmt":"$325K","rank":755},{"m":"Beckley, WV","total_assets":9,"total_amount":322080,"total_fmt":"$322K","rank":756},{"m":"Muncie, IN","total_assets":6,"total_amount":314319,"total_fmt":"$314K","rank":757},{"m":"Gainesville, TX","total_assets":7,"total_amount":311559,"total_fmt":"$312K","rank":758},{"m":"Town of Pecos, TX","total_assets":1,"total_amount":308728,"total_fmt":"$309K","rank":759},{"m":"Arkadelphia, AR","total_assets":2,"total_amount":305964,"total_fmt":"$306K","rank":760},{"m":"Stephenville, TX","total_assets":2,"total_amount":305547,"total_fmt":"$306K","rank":761},{"m":"El Campo, TX","total_assets":2,"total_amount":304280,"total_fmt":"$304K","rank":762},{"m":"Shelbyville, TN","total_assets":3,"total_amount":300725,"total_fmt":"$301K","rank":763},{"m":"Emporia, KS","total_assets":6,"total_amount":298538,"total_fmt":"$299K","rank":764},{"m":"Port Lavaca, TX","total_assets":2,"total_amount":292989,"total_fmt":"$293K","rank":765},{"m":"Coamo, PR","total_assets":2,"total_amount":291169,"total_fmt":"$291K","rank":766},{"m":"Dumas, TX","total_assets":2,"total_amount":288131,"total_fmt":"$288K","rank":767},{"m":"Hobbs, NM","total_assets":2,"total_amount":281122,"total_fmt":"$281K","rank":768},{"m":"Malvern, AR","total_assets":4,"total_amount":279373,"total_fmt":"$279K","rank":769},{"m":"Oskaloosa, IA","total_assets":3,"total_amount":271966,"total_fmt":"$272K","rank":770},{"m":"Ashland, OH","total_assets":2,"total_amount":268689,"total_fmt":"$269K","rank":771},{"m":"Fort Dodge, IA","total_assets":3,"total_amount":263763,"total_fmt":"$264K","rank":772},{"m":"Union City, TN","total_assets":3,"total_amount":256536,"total_fmt":"$257K","rank":773},{"m":"Decatur, IN","total_assets":3,"total_amount":249533,"total_fmt":"$250K","rank":774},{"m":"Logansport, IN","total_assets":4,"total_amount":246458,"total_fmt":"$246K","rank":775},{"m":"Garden City, KS","total_assets":1,"total_amount":237328,"total_fmt":"$237K","rank":776},{"m":"North Wilkesboro, NC","total_assets":3,"total_amount":235550,"total_fmt":"$236K","rank":777},{"m":"Farmington, NM","total_assets":4,"total_amount":232700,"total_fmt":"$233K","rank":778},{"m":"Jonesboro, AR","total_assets":6,"total_amount":225581,"total_fmt":"$226K","rank":779},{"m":"Brookings, OR","total_assets":1,"total_amount":207920,"total_fmt":"$208K","rank":780},{"m":"Menomonie, WI","total_assets":3,"total_amount":207854,"total_fmt":"$208K","rank":781},{"m":"Clewiston, FL","total_assets":5,"total_amount":207219,"total_fmt":"$207K","rank":782},{"m":"Harrison, AR","total_assets":6,"total_amount":200164,"total_fmt":"$200K","rank":783},{"m":"Roswell, NM","total_assets":4,"total_amount":199197,"total_fmt":"$199K","rank":784},{"m":"Mount Vernon, OH","total_assets":1,"total_amount":197295,"total_fmt":"$197K","rank":785},{"m":"Crawfordsville, IN","total_assets":1,"total_amount":193983,"total_fmt":"$194K","rank":786},{"m":"Cody, WY","total_assets":2,"total_amount":186857,"total_fmt":"$187K","rank":787},{"m":"Sweetwater, TX","total_assets":2,"total_amount":181697,"total_fmt":"$182K","rank":788},{"m":"Cullman, AL","total_assets":4,"total_amount":179314,"total_fmt":"$179K","rank":789},{"m":"Washington, NC","total_assets":2,"total_amount":177864,"total_fmt":"$178K","rank":790},{"m":"Kokomo, IN","total_assets":7,"total_amount":171968,"total_fmt":"$172K","rank":791},{"m":"Mason City, IA","total_assets":1,"total_amount":168641,"total_fmt":"$169K","rank":792},{"m":"Seymour, IN","total_assets":4,"total_amount":168403,"total_fmt":"$168K","rank":793},{"m":"Greencastle, IN","total_assets":3,"total_amount":165174,"total_fmt":"$165K","rank":794},{"m":"Americus, GA","total_assets":1,"total_amount":161751,"total_fmt":"$162K","rank":795},{"m":"The Dalles, OR","total_assets":2,"total_amount":159442,"total_fmt":"$159K","rank":796},{"m":"Chillicothe, OH","total_assets":4,"total_amount":157792,"total_fmt":"$158K","rank":797},{"m":"Gallipolis, OH","total_assets":2,"total_amount":157384,"total_fmt":"$157K","rank":798},{"m":"Willmar, MN","total_assets":2,"total_amount":153034,"total_fmt":"$153K","rank":799},{"m":"Bloomsburg-Berwick, PA","total_assets":4,"total_amount":146872,"total_fmt":"$147K","rank":800},{"m":"Rock Springs, WY","total_assets":1,"total_amount":139423,"total_fmt":"$139K","rank":801},{"m":"Mexico, MO","total_assets":4,"total_amount":132595,"total_fmt":"$133K","rank":802},{"m":"Jefferson, GA","total_assets":3,"total_amount":131700,"total_fmt":"$132K","rank":803},{"m":"Ruidoso, NM","total_assets":2,"total_amount":123769,"total_fmt":"$124K","rank":804},{"m":"Cornelia, GA","total_assets":3,"total_amount":123660,"total_fmt":"$124K","rank":805},{"m":"Macomb, IL","total_assets":2,"total_amount":123075,"total_fmt":"$123K","rank":806},{"m":"Spencer, IA","total_assets":3,"total_amount":120604,"total_fmt":"$121K","rank":807},{"m":"Toccoa, GA","total_assets":1,"total_amount":114867,"total_fmt":"$115K","rank":808},{"m":"Centralia, IL","total_assets":3,"total_amount":108144,"total_fmt":"$108K","rank":809},{"m":"Mitchell, SD","total_assets":2,"total_amount":97989,"total_fmt":"$98K","rank":810},{"m":"Eufaula, AL-GA","total_assets":5,"total_amount":96302,"total_fmt":"$96K","rank":811},{"m":"Martinsville, VA","total_assets":8,"total_amount":96043,"total_fmt":"$96K","rank":812},{"m":"Woodward, OK","total_assets":6,"total_amount":87027,"total_fmt":"$87K","rank":813},{"m":"Kendallville, IN","total_assets":4,"total_amount":86516,"total_fmt":"$87K","rank":814},{"m":"Guayama, PR","total_assets":1,"total_amount":83672,"total_fmt":"$84K","rank":815},{"m":"Taylorville, IL","total_assets":3,"total_amount":77353,"total_fmt":"$77K","rank":816},{"m":"Pontiac, IL","total_assets":2,"total_amount":76107,"total_fmt":"$76K","rank":817},{"m":"Winnemucca, NV","total_assets":1,"total_amount":75568,"total_fmt":"$76K","rank":818},{"m":"Safford, AZ","total_assets":2,"total_amount":75047,"total_fmt":"$75K","rank":819},{"m":"Nacogdoches, TX","total_assets":1,"total_amount":74195,"total_fmt":"$74K","rank":820},{"m":"Lake City, FL","total_assets":4,"total_amount":70310,"total_fmt":"$70K","rank":821},{"m":"Baker City, OR","total_assets":1,"total_amount":69956,"total_fmt":"$70K","rank":822},{"m":"Thomaston, GA","total_assets":1,"total_amount":68525,"total_fmt":"$69K","rank":823},{"m":"Lewistown, PA","total_assets":2,"total_amount":67858,"total_fmt":"$68K","rank":824},{"m":"Eagle Pass, TX","total_assets":2,"total_amount":67575,"total_fmt":"$68K","rank":825},{"m":"Corsicana, TX","total_assets":3,"total_amount":66531,"total_fmt":"$67K","rank":826},{"m":"Ottumwa, IA","total_assets":2,"total_amount":60690,"total_fmt":"$61K","rank":827},{"m":"Auburn, IN","total_assets":4,"total_amount":59405,"total_fmt":"$59K","rank":828},{"m":"McPherson, KS","total_assets":2,"total_amount":57846,"total_fmt":"$58K","rank":829},{"m":"St. Marys, PA","total_assets":2,"total_amount":57202,"total_fmt":"$57K","rank":830},{"m":"Rockingham, NC","total_assets":2,"total_amount":54622,"total_fmt":"$55K","rank":831},{"m":"Gloversville, NY","total_assets":1,"total_amount":54545,"total_fmt":"$55K","rank":832},{"m":"Okeechobee, FL","total_assets":1,"total_amount":49929,"total_fmt":"$50K","rank":833},{"m":"Weatherford, OK","total_assets":2,"total_amount":48540,"total_fmt":"$49K","rank":834},{"m":"Huron, SD","total_assets":1,"total_amount":46091,"total_fmt":"$46K","rank":835},{"m":"Cleveland, MS","total_assets":3,"total_amount":44928,"total_fmt":"$45K","rank":836},{"m":"Uvalde, TX","total_assets":2,"total_amount":42810,"total_fmt":"$43K","rank":837},{"m":"Petoskey, MI","total_assets":1,"total_amount":41858,"total_fmt":"$42K","rank":838},{"m":"Silver City, NM","total_assets":1,"total_amount":39270,"total_fmt":"$39K","rank":839},{"m":"Dixon, IL","total_assets":1,"total_amount":38881,"total_fmt":"$39K","rank":840},{"m":"Price, UT","total_assets":1,"total_amount":33157,"total_fmt":"$33K","rank":841},{"m":"Sturgis, MI","total_assets":3,"total_amount":31315,"total_fmt":"$31K","rank":842},{"m":"Ontario, OR-ID","total_assets":2,"total_amount":30545,"total_fmt":"$31K","rank":843},{"m":"Big Spring, TX","total_assets":1,"total_amount":28693,"total_fmt":"$29K","rank":844},{"m":"Effingham, IL","total_assets":2,"total_amount":27686,"total_fmt":"$28K","rank":845},{"m":"Lewisburg, TN","total_assets":1,"total_amount":27536,"total_fmt":"$28K","rank":846},{"m":"Platteville, WI","total_assets":2,"total_amount":26970,"total_fmt":"$27K","rank":847},{"m":"Ada, OK","total_assets":2,"total_amount":26141,"total_fmt":"$26K","rank":848},{"m":"Newport, OR","total_assets":1,"total_amount":25000,"total_fmt":"$25K","rank":849},{"m":"Tiffin, OH","total_assets":1,"total_amount":22671,"total_fmt":"$23K","rank":850},{"m":"Galesburg, IL","total_assets":2,"total_amount":22137,"total_fmt":"$22K","rank":851},{"m":"Bishop, CA","total_assets":1,"total_amount":20497,"total_fmt":"$20K","rank":852},{"m":"Great Bend, KS","total_assets":3,"total_amount":19650,"total_fmt":"$20K","rank":853},{"m":"Fairmont, MN","total_assets":1,"total_amount":17735,"total_fmt":"$18K","rank":854},{"m":"Tifton, GA","total_assets":1,"total_amount":17176,"total_fmt":"$17K","rank":855},{"m":"Marion, NC","total_assets":1,"total_amount":16390,"total_fmt":"$16K","rank":856},{"m":"Kankakee, IL","total_assets":2,"total_amount":15790,"total_fmt":"$16K","rank":857},{"m":"Newberry, SC","total_assets":1,"total_amount":15000,"total_fmt":"$15K","rank":858},{"m":"Aberdeen, SD","total_assets":1,"total_amount":14888,"total_fmt":"$15K","rank":859},{"m":"Greenville, MS","total_assets":1,"total_amount":13981,"total_fmt":"$14K","rank":860},{"m":"Las Vegas, NM","total_assets":1,"total_amount":13930,"total_fmt":"$14K","rank":861},{"m":"Raymondville, TX","total_assets":1,"total_amount":12498,"total_fmt":"$12K","rank":862},{"m":"Marion, OH","total_assets":2,"total_amount":12433,"total_fmt":"$12K","rank":863},{"m":"Owosso, MI","total_assets":1,"total_amount":12390,"total_fmt":"$12K","rank":864},{"m":"Portsmouth, OH","total_assets":1,"total_amount":11664,"total_fmt":"$12K","rank":865},{"m":"Bay City, TX","total_assets":1,"total_amount":11250,"total_fmt":"$11K","rank":866},{"m":"Hays, KS","total_assets":2,"total_amount":10584,"total_fmt":"$11K","rank":867},{"m":"Pittsburg, KS","total_assets":1,"total_amount":10556,"total_fmt":"$11K","rank":868},{"m":"Frankfort, IN","total_assets":1,"total_amount":9289,"total_fmt":"$9K","rank":869},{"m":"Vineyard Haven, MA","total_assets":1,"total_amount":8691,"total_fmt":"$9K","rank":870},{"m":"Arcadia, FL","total_assets":1,"total_amount":8050,"total_fmt":"$8K","rank":871},{"m":"Dodge City, KS","total_assets":2,"total_amount":8000,"total_fmt":"$8K","rank":872},{"m":"Utuado, PR","total_assets":2,"total_amount":7551,"total_fmt":"$8K","rank":873},{"m":"Pampa, TX","total_assets":1,"total_amount":7500,"total_fmt":"$8K","rank":874},{"m":"McComb, MS","total_assets":1,"total_amount":6773,"total_fmt":"$7K","rank":875},{"m":"Atchison, KS","total_assets":2,"total_amount":6728,"total_fmt":"$7K","rank":876},{"m":"Rice Lake, WI","total_assets":2,"total_amount":6459,"total_fmt":"$6K","rank":877},{"m":"Gillette, WY","total_assets":2,"total_amount":4096,"total_fmt":"$4K","rank":878},{"m":"Guymon, OK","total_assets":1,"total_amount":3731,"total_fmt":"$4K","rank":879},{"m":"Cambridge, OH","total_assets":1,"total_amount":2965,"total_fmt":"$3K","rank":880},{"m":"Washington Court House, OH","total_assets":1,"total_amount":2914,"total_fmt":"$3K","rank":881},{"m":"Danville, KY","total_assets":1,"total_amount":2000,"total_fmt":"$2K","rank":882},{"m":"Forrest City, AR","total_assets":1,"total_amount":94,"total_fmt":"$0K","rank":883},{"m":"Allentown-Bethlehem-East Stroudsburg, PA-NJ","total_assets":1,"total_amount":0,"total_fmt":"$0K","rank":884},{"m":"Gallup, NM","total_assets":1,"total_amount":0,"total_fmt":"$0K","rank":885},{"m":"ONLINE","total_assets":4,"total_amount":0,"total_fmt":"$0K","rank":886},{"m":"nan","total_assets":63,"total_amount":0,"total_fmt":"$0K","rank":887}]
